{" Groudon-Primal     ":{"rank":" 1    ","usage":" 79.15958% ","change":"1.0068100000000015%","rankChange":0}," Xerneas            ":{"rank":" 2    ","usage":" 48.96055% ","change":"2.932469999999995%","rankChange":1}," Yveltal            ":{"rank":" 3    ","usage":" 43.72324% ","change":"-2.624840000000006%","rankChange":-1}," Arceus             ":{"rank":" 4    ","usage":" 28.21766% ","change":"0.5244599999999977%","rankChange":0}," Lunala             ":{"rank":" 5    ","usage":" 23.25309% ","change":"3.7818299999999994%","rankChange":1}," Salamence-Mega     ":{"rank":" 6    ","usage":" 22.76181% ","change":"1.5887600000000006%","rankChange":-1}," Gengar-Mega        ":{"rank":" 7    ","usage":" 17.59353% ","change":"-1.87772%","rankChange":0}," Deoxys-Attack      ":{"rank":" 8    ","usage":" 17.52845% ","change":"2.530999999999999%","rankChange":1}," Lucario-Mega       ":{"rank":" 9    ","usage":" 16.01756% ","change":"0.8398599999999998%","rankChange":-1}," Solgaleo           ":{"rank":" 10   ","usage":" 15.75302% ","change":"4.603759999999999%","rankChange":7}," Zygarde            ":{"rank":" 11   ","usage":" 15.52786% ","change":"3.6402300000000007%","rankChange":5}," Arceus-Water       ":{"rank":" 12   ","usage":" 14.08012% ","change":"-0.007299999999998974%","rankChange":-1}," Kyogre-Primal      ":{"rank":" 13   ","usage":" 13.00111% ","change":"-0.6032199999999985%","rankChange":0}," Giratina-Origin    ":{"rank":" 14   ","usage":" 12.97521% ","change":"0.4205900000000007%","rankChange":1}," Arceus-Ground      ":{"rank":" 15   ","usage":" 12.73208% ","change":"-0.9031300000000009%","rankChange":-3}," Ho-Oh              ":{"rank":" 16   ","usage":" 11.28903% ","change":"-1.35323%","rankChange":-2}," Magearna           ":{"rank":" 17   ","usage":" 11.18357% ","change":"-3.1274499999999996%","rankChange":-7}," Deoxys-Speed       ":{"rank":" 18   ","usage":" 10.76245% ","change":"2.0089799999999993%","rankChange":1}," Arceus-Ghost       ":{"rank":" 19   ","usage":"  8.53166% ","change":"0.64412%","rankChange":1}," Rayquaza           ":{"rank":" 20   ","usage":"  8.11655% ","change":"-2.978999999999999%","rankChange":-2}," Arceus-Fairy       ":{"rank":" 21   ","usage":"  7.69787% ","change":"1.6422999999999996%","rankChange":5}," Lugia              ":{"rank":" 22   ","usage":"  7.19500% ","change":"0.18852000000000046%","rankChange":1}," Kyurem-White       ":{"rank":" 23   ","usage":"  6.93398% ","change":"-0.88415%","rankChange":-2}," Ferrothorn         ":{"rank":" 24   ","usage":"  6.17496% ","change":"-0.5776300000000001%","rankChange":0}," Arceus-Dark        ":{"rank":" 25   ","usage":"  6.15717% ","change":"0.45826999999999973%","rankChange":2}," Ditto              ":{"rank":" 26   ","usage":"  5.90041% ","change":"0.23911999999999978%","rankChange":2}," Smeargle           ":{"rank":" 27   ","usage":"  5.89825% ","change":"-1.11489%","rankChange":-5}," Tapu Lele          ":{"rank":" 28   ","usage":"  5.59640% ","change":"0.8762999999999996%","rankChange":4}," Mewtwo             ":{"rank":" 29   ","usage":"  5.29650% ","change":"-0.03462999999999994%","rankChange":0}," Aegislash          ":{"rank":" 30   ","usage":"  4.47425% ","change":"-0.6203200000000004%","rankChange":0}," Darkrai            ":{"rank":" 31   ","usage":"  4.30712% ","change":"1.3959800000000002%","rankChange":8}," Excadrill          ":{"rank":" 32   ","usage":"  3.88390% ","change":"-2.4859499999999994%","rankChange":-7}," Kangaskhan-Mega    ":{"rank":" 33   ","usage":"  3.86122% ","change":"1.10887%","rankChange":7}," Dialga             ":{"rank":" 34   ","usage":"  3.71225% ","change":"0.4094199999999999%","rankChange":1}," Chansey            ":{"rank":" 35   ","usage":"  3.26566% ","change":"-0.35017999999999994%","rankChange":-2}," Toxapex            ":{"rank":" 36   ","usage":"  3.23441% ","change":"1.03146%","rankChange":11}," Sableye-Mega       ":{"rank":" 37   ","usage":"  2.96137% ","change":"0.46784000000000026%","rankChange":8}," Pheromosa          ":{"rank":" 38   ","usage":"  2.94801% ","change":"0.22704000000000013%","rankChange":3}," Palkia             ":{"rank":" 39   ","usage":"  2.85385% ","change":"1.1832799999999999%","rankChange":15}," Shuckle            ":{"rank":" 40   ","usage":"  2.79642% ","change":"0.2469999999999999%","rankChange":2}," Giratina           ":{"rank":" 41   ","usage":"  2.74608% ","change":"-0.8526599999999998%","rankChange":-7}," Shaymin-Sky        ":{"rank":" 42   ","usage":"  2.63819% ","change":"-0.44618%","rankChange":-4}," Arceus-Steel       ":{"rank":" 43   ","usage":"  2.26561% ","change":"-2.5670100000000002%","rankChange":-12}," Landorus-Therian   ":{"rank":" 44   ","usage":"  2.25028% ","change":"0.83159%","rankChange":15}," Blissey            ":{"rank":" 45   ","usage":"  2.11935% ","change":"0.8890099999999999%","rankChange":23}," Arceus-Rock        ":{"rank":" 46   ","usage":"  1.91531% ","change":"-0.58375%","rankChange":-2}," Cloyster           ":{"rank":" 47   ","usage":"  1.85872% ","change":"0.2817099999999999%","rankChange":9}," Kartana            ":{"rank":" 48   ","usage":"  1.83458% ","change":"0.5762200000000002%","rankChange":18}," Scolipede          ":{"rank":" 49   ","usage":"  1.83361% ","change":"-0.5547700000000002%","rankChange":-3}," Muk-Alola          ":{"rank":" 50   ","usage":"  1.78143% ","change":"-1.32324%","rankChange":-13}," Tyranitar          ":{"rank":" 51   ","usage":"  1.74939% ","change":"-0.057600000000000096%","rankChange":1}," Kyogre             ":{"rank":" 52   ","usage":"  1.70924% ","change":"0.019560000000000022%","rankChange":1}," Genesect           ":{"rank":" 53   ","usage":"  1.66329% ","change":"-0.25089000000000006%","rankChange":-3}," Skarmory           ":{"rank":" 54   ","usage":"  1.63883% ","change":"0.43561000000000005%","rankChange":15}," Blaziken           ":{"rank":" 55   ","usage":"  1.60622% ","change":"-0.45264000000000015%","rankChange":-7}," Zekrom             ":{"rank":" 56   ","usage":"  1.54008% ","change":"-0.03577000000000008%","rankChange":1}," Bronzong           ":{"rank":" 57   ","usage":"  1.41010% ","change":"0.011539999999999884%","rankChange":3}," Tapu Koko          ":{"rank":" 58   ","usage":"  1.40036% ","change":"0.3665100000000001%","rankChange":15}," Scizor-Mega        ":{"rank":" 59   ","usage":"  1.38519% ","change":"-0.4357300000000002%","rankChange":-8}," Scizor             ":{"rank":" 60   ","usage":"  1.33147% ","change":"-0.10444000000000009%","rankChange":-2}," Dugtrio            ":{"rank":" 61   ","usage":"  1.28575% ","change":"-0.006220000000000114%","rankChange":3}," Greninja-Ash       ":{"rank":" 62   ","usage":"  1.22469% ","change":"0.16969999999999996%","rankChange":10}," Klefki             ":{"rank":" 63   ","usage":"  1.22393% ","change":"-0.13853000000000004%","rankChange":-1}," Arceus-Dragon      ":{"rank":" 64   ","usage":"  1.22215% ","change":"0.36555000000000004%","rankChange":13}," Landorus           ":{"rank":" 65   ","usage":"  1.19151% ","change":"-0.79244%","rankChange":-16}," Celesteela         ":{"rank":" 66   ","usage":"  1.14909% ","change":"-2.07308%","rankChange":-30}," Slowbro-Mega       ":{"rank":" 67   ","usage":"  1.06969% ","change":"-0.25841999999999987%","rankChange":-4}," Garchomp           ":{"rank":" 68   ","usage":"  1.01311% ","change":"0.4232499999999999%","rankChange":16}," Eevee              ":{"rank":" 69   ","usage":"  0.95710% ","change":"-0.43901%","rankChange":-8}," Metagross-Mega     ":{"rank":" 70   ","usage":"  0.86905% ","change":"-0.07513000000000003%","rankChange":4}," Xurkitree          ":{"rank":" 71   ","usage":"  0.85988% ","change":"0.43640999999999996%","rankChange":19}," Espeon             ":{"rank":" 72   ","usage":"  0.85747% ","change":"-1.64897%","rankChange":-29}," Arceus-Poison      ":{"rank":" 73   ","usage":"  0.77712% ","change":"0.17820999999999998%","rankChange":10}," Greninja           ":{"rank":" 74   ","usage":"  0.76442% ","change":"0.19918999999999998%","rankChange":11}," Whimsicott         ":{"rank":" 75   ","usage":"  0.63674% ","change":"0.47733%","rankChange":41}," Mimikyu            ":{"rank":" 76   ","usage":"  0.59476% ","change":"-0.08549000000000007%","rankChange":4}," Pyukumuku          ":{"rank":" 77   ","usage":"  0.57412% ","change":"0.019220000000000015%","rankChange":10}," Nihilego           ":{"rank":" 78   ","usage":"  0.52118% ","change":"0.29059999999999997%","rankChange":23}," Clefable           ":{"rank":" 79   ","usage":"  0.48292% ","change":"-1.1711799999999999%","rankChange":-24}," Mew                ":{"rank":" 80   ","usage":"  0.47418% ","change":"-0.61406%","rankChange":-9}," Krookodile         ":{"rank":" 81   ","usage":"  0.45128% ","change":"-0.43625%","rankChange":-5}," Groudon            ":{"rank":" 82   ","usage":"  0.44842% ","change":"-0.45152%","rankChange":-7}," Tapu Fini          ":{"rank":" 83   ","usage":"  0.44132% ","change":"-0.36288000000000004%","rankChange":-5}," Deoxys-Defense     ":{"rank":" 84   ","usage":"  0.39704% ","change":"0.04252%","rankChange":9}," Arceus-Grass       ":{"rank":" 85   ","usage":"  0.36988% ","change":"-0.04053000000000001%","rankChange":6}," Arceus-Electric    ":{"rank":" 86   ","usage":"  0.35907% ","change":"-0.08917999999999998%","rankChange":3}," Gyarados-Mega      ":{"rank":" 87   ","usage":"  0.34562% ","change":"0.16857999999999998%","rankChange":23}," Arceus-Flying      ":{"rank":" 88   ","usage":"  0.33704% ","change":"-0.14006999999999997%","rankChange":0}," Gliscor            ":{"rank":" 89   ","usage":"  0.33516% ","change":"0.07855000000000001%","rankChange":10}," Reshiram           ":{"rank":" 90   ","usage":"  0.32511% ","change":"0.05254000000000003%","rankChange":7}," Tapu Bulu          ":{"rank":" 91   ","usage":"  0.30023% ","change":"-0.25993%","rankChange":-5}," Wobbuffet          ":{"rank":" 92   ","usage":"  0.29755% ","change":"-0.005400000000000016%","rankChange":4}," Latias             ":{"rank":" 93   ","usage":"  0.29569% ","change":"-0.06427%","rankChange":-1}," Galvantula         ":{"rank":" 94   ","usage":"  0.28919% ","change":"0.16399%","rankChange":29}," Forretress         ":{"rank":" 95   ","usage":"  0.27804% ","change":"0.06737000000000001%","rankChange":11}," Latios             ":{"rank":" 96   ","usage":"  0.27209% ","change":"0.05024999999999999%","rankChange":7}," Sylveon            ":{"rank":" 97   ","usage":"  0.27064% ","change":"-0.9649000000000001%","rankChange":-30}," Minior             ":{"rank":" 98   ","usage":"  0.25208% ","change":"0.14489000000000002%","rankChange":31}," Vaporeon           ":{"rank":" 99   ","usage":"  0.24930% ","change":"-1.03707%","rankChange":-34}," Breloom            ":{"rank":" 100  ","usage":"  0.24377% ","change":"0.15448%","rankChange":39}," Zygarde-10%        ":{"rank":" 101  ","usage":"  0.22893% ","change":"0.003959999999999991%","rankChange":1}," Decidueye          ":{"rank":" 102  ","usage":"  0.22529% ","change":"0.12524%","rankChange":31}," Tentacruel         ":{"rank":" 103  ","usage":"  0.22170% ","change":"0.05583000000000002%","rankChange":10}," Buzzwole           ":{"rank":" 104  ","usage":"  0.21980% ","change":"-0.46555%","rankChange":-25}," Arceus-Ice         ":{"rank":" 105  ","usage":"  0.21052% ","change":"-0.46402%","rankChange":-24}," Jirachi            ":{"rank":" 106  ","usage":"  0.20703% ","change":"-0.057709999999999984%","rankChange":-8}," Salamence          ":{"rank":" 107  ","usage":"  0.20022% ","change":"0.05199000000000001%","rankChange":10}," Bewear             ":{"rank":" 108  ","usage":"  0.19989% ","change":"0.10957000000000001%","rankChange":30}," Mamoswine          ":{"rank":" 109  ","usage":"  0.19758% ","change":"0.033320000000000016%","rankChange":5}," Hoopa-Unbound      ":{"rank":" 110  ","usage":"  0.19677% ","change":"-0.012399999999999994%","rankChange":-3}," Necrozma           ":{"rank":" 111  ","usage":"  0.19302% ","change":"0.054409999999999986%","rankChange":8}," Umbreon            ":{"rank":" 112  ","usage":"  0.19282% ","change":"-0.15811000000000003%","rankChange":-18}," Mr. Mime           ":{"rank":" 113  ","usage":"  0.18797% ","change":"-0.94373%","rankChange":-43}," Alakazam-Mega      ":{"rank":" 114  ","usage":"  0.17415% ","change":"0.05584%","rankChange":10}," Aerodactyl-Mega    ":{"rank":" 115  ","usage":"  0.16295% ","change":"-0.18609%","rankChange":-20}," Dragonite          ":{"rank":" 116  ","usage":"  0.15870% ","change":"0.025180000000000008%","rankChange":4}," Terrakion          ":{"rank":" 117  ","usage":"  0.14429% ","change":"-0.06650999999999999%","rankChange":-12}," Charizard-Mega-X   ":{"rank":" 118  ","usage":"  0.14297% ","change":"-0.04621999999999998%","rankChange":-9}," Victini            ":{"rank":" 119  ","usage":"  0.14025% ","change":"0.08280000000000001%","rankChange":50}," Gengar             ":{"rank":" 120  ","usage":"  0.14009% ","change":"-0.024040000000000006%","rankChange":-5}," Amoonguss          ":{"rank":" 121  ","usage":"  0.13992% ","change":"0.0633%","rankChange":24}," Weavile            ":{"rank":" 122  ","usage":"  0.13582% ","change":"0.04336999999999999%","rankChange":14}," Shedinja           ":{"rank":" 123  ","usage":"  0.13525% ","change":"-0.07987%","rankChange":-19}," Marowak-Alola      ":{"rank":" 124  ","usage":"  0.13284% ","change":"-0.0431%","rankChange":-13}," Porygon-Z          ":{"rank":" 125  ","usage":"  0.12951% ","change":"0.05836999999999999%","rankChange":33}," Heatran            ":{"rank":" 126  ","usage":"  0.12671% ","change":"-0.000060000000000004494%","rankChange":-4}," Arceus-Fighting    ":{"rank":" 127  ","usage":"  0.12424% ","change":"0.04297000000000001%","rankChange":14}," Azelf              ":{"rank":" 128  ","usage":"  0.11999% ","change":"0.0868%","rankChange":79}," Incineroar         ":{"rank":" 129  ","usage":"  0.11436% ","change":"0.06276000000000001%","rankChange":49}," Venusaur-Mega      ":{"rank":" 130  ","usage":"  0.11394% ","change":"-0.54401%","rankChange":-48}," Ninetales-Alola    ":{"rank":" 131  ","usage":"  0.11051% ","change":"-0.057120000000000004%","rankChange":-19}," Drapion            ":{"rank":" 132  ","usage":"  0.10961% ","change":"0.1016%","rankChange":187}," Kyurem-Black       ":{"rank":" 133  ","usage":"  0.10801% ","change":"0.004470000000000002%","rankChange":-2}," Serperior          ":{"rank":" 134  ","usage":"  0.10712% ","change":"0.026050000000000004%","rankChange":8}," Kommo-o            ":{"rank":" 135  ","usage":"  0.10682% ","change":"0.0032299999999999968%","rankChange":-5}," Glalie-Mega        ":{"rank":" 136  ","usage":"  0.10662% ","change":"0.10197%","rankChange":237}," Sableye            ":{"rank":" 137  ","usage":"  0.10653% ","change":"0.06520000000000001%","rankChange":56}," Golisopod          ":{"rank":" 138  ","usage":"  0.10129% ","change":"0.03728000000000001%","rankChange":25}," Cottonee           ":{"rank":" 139  ","usage":"  0.10069% ","change":"0.09788%","rankChange":271}," Guzzlord           ":{"rank":" 140  ","usage":"  0.10002% ","change":"0.03906%","rankChange":25}," Flygon             ":{"rank":" 141  ","usage":"  0.09961% ","change":"-0.09777%","rankChange":-33}," Salazzle           ":{"rank":" 142  ","usage":"  0.09945% ","change":"-0.0013999999999999985%","rankChange":-10}," Araquanid          ":{"rank":" 143  ","usage":"  0.09810% ","change":"0.02359%","rankChange":5}," Dhelmise           ":{"rank":" 144  ","usage":"  0.09764% ","change":"0.030100000000000002%","rankChange":18}," Jolteon            ":{"rank":" 145  ","usage":"  0.09403% ","change":"0.021589999999999998%","rankChange":8}," Bisharp            ":{"rank":" 146  ","usage":"  0.09222% ","change":"-0.007540000000000005%","rankChange":-12}," Ninjask            ":{"rank":" 147  ","usage":"  0.08990% ","change":"0.010659999999999989%","rankChange":-3}," Milotic            ":{"rank":" 148  ","usage":"  0.08743% ","change":"0.014949999999999991%","rankChange":4}," Charizard-Mega-Y   ":{"rank":" 149  ","usage":"  0.08234% ","change":"0.007580000000000003%","rankChange":-2}," Primarina          ":{"rank":" 150  ","usage":"  0.08190% ","change":"0.0010700000000000015%","rankChange":-7}," Diancie            ":{"rank":" 151  ","usage":"  0.08172% ","change":"0.0482%","rankChange":54}," Cresselia          ":{"rank":" 152  ","usage":"  0.08131% ","change":"0.060669999999999995%","rankChange":92}," Hydreigon          ":{"rank":" 153  ","usage":"  0.08030% ","change":"0.006919999999999996%","rankChange":-2}," Arceus-Fire        ":{"rank":" 154  ","usage":"  0.07856% ","change":"-0.17379%","rankChange":-54}," Lycanroc           ":{"rank":" 155  ","usage":"  0.07794% ","change":"0.006449999999999997%","rankChange":1}," Talonflame         ":{"rank":" 156  ","usage":"  0.07761% ","change":"0.03415%","rankChange":34}," Togekiss           ":{"rank":" 157  ","usage":"  0.07709% ","change":"-0.014899999999999997%","rankChange":-20}," Froslass           ":{"rank":" 158  ","usage":"  0.07464% ","change":"-0.03556000000000001%","rankChange":-31}," Goodra             ":{"rank":" 159  ","usage":"  0.07397% ","change":"0.02133999999999999%","rankChange":17}," Raichu-Alola       ":{"rank":" 160  ","usage":"  0.07162% ","change":"0.024690000000000004%","rankChange":27}," Sawk               ":{"rank":" 161  ","usage":"  0.07056% ","change":"0.06859%","rankChange":282}," Staraptor          ":{"rank":" 162  ","usage":"  0.07035% ","change":"0.04971%","rankChange":81}," Magnezone          ":{"rank":" 163  ","usage":"  0.06950% ","change":"0.013870000000000007%","rankChange":8}," Azumarill          ":{"rank":" 164  ","usage":"  0.06893% ","change":"0.015590000000000007%","rankChange":11}," Volcarona          ":{"rank":" 165  ","usage":"  0.06846% ","change":"0.00032999999999999696%","rankChange":-4}," Starmie            ":{"rank":" 166  ","usage":"  0.06770% ","change":"0.042839999999999996%","rankChange":62}," Claydol            ":{"rank":" 167  ","usage":"  0.06582% ","change":"0.060320000000000006%","rankChange":190}," Porygon2           ":{"rank":" 168  ","usage":"  0.06549% ","change":"-0.04480999999999999%","rankChange":-42}," Infernape          ":{"rank":" 169  ","usage":"  0.06300% ","change":"0.022830000000000003%","rankChange":28}," Arcanine           ":{"rank":" 170  ","usage":"  0.06279% ","change":"0.012789999999999996%","rankChange":11}," Durant             ":{"rank":" 171  ","usage":"  0.06230% ","change":"0.013580000000000002%","rankChange":14}," Comfey             ":{"rank":" 172  ","usage":"  0.05858% ","change":"0.007980000000000001%","rankChange":7}," Garchomp-Mega      ":{"rank":" 173  ","usage":"  0.05579% ","change":"-0.0005199999999999996%","rankChange":-3}," Rotom-Wash         ":{"rank":" 174  ","usage":"  0.05394% ","change":"-0.0007999999999999952%","rankChange":-2}," Ariados            ":{"rank":" 175  ","usage":"  0.05372% ","change":"0.009909999999999995%","rankChange":14}," Wishiwashi         ":{"rank":" 176  ","usage":"  0.05330% ","change":"0.02514%","rankChange":44}," Gothitelle         ":{"rank":" 177  ","usage":"  0.05235% ","change":"-0.04488999999999999%","rankChange":-42}," Snorlax            ":{"rank":" 178  ","usage":"  0.04965% ","change":"-0.0008099999999999982%","rankChange":2}," Mudsdale           ":{"rank":" 179  ","usage":"  0.04893% ","change":"0.01573%","rankChange":27}," Swampert           ":{"rank":" 180  ","usage":"  0.04836% ","change":"0.02207%","rankChange":45}," Chandelure         ":{"rank":" 181  ","usage":"  0.04686% ","change":"-0.013249999999999998%","rankChange":-15}," Lucario            ":{"rank":" 182  ","usage":"  0.04581% ","change":"0.016809999999999995%","rankChange":35}," Thundurus          ":{"rank":" 183  ","usage":"  0.04547% ","change":"0.007439999999999995%","rankChange":16}," Suicune            ":{"rank":" 184  ","usage":"  0.04331% ","change":"-0.10293000000000001%","rankChange":-66}," Arceus-Psychic     ":{"rank":" 185  ","usage":"  0.04312% ","change":"0.018199999999999997%","rankChange":42}," Vikavolt           ":{"rank":" 186  ","usage":"  0.04234% ","change":"0.02083%","rankChange":54}," Tsareena           ":{"rank":" 187  ","usage":"  0.04197% ","change":"0.004729999999999998%","rankChange":13}," Crobat             ":{"rank":" 188  ","usage":"  0.04169% ","change":"-0.030070000000000006%","rankChange":-33}," Gyarados           ":{"rank":" 189  ","usage":"  0.04155% ","change":"-0.010350000000000005%","rankChange":-12}," Arceus-Bug         ":{"rank":" 190  ","usage":"  0.04104% ","change":"0.035089999999999996%","rankChange":156}," Exeggutor-Alola    ":{"rank":" 191  ","usage":"  0.04086% ","change":"0.01821%","rankChange":41}," Metagross          ":{"rank":" 192  ","usage":"  0.03925% ","change":"-0.01824%","rankChange":-24}," Deoxys             ":{"rank":" 193  ","usage":"  0.03885% ","change":"-0.036770000000000004%","rankChange":-47}," Avalugg            ":{"rank":" 194  ","usage":"  0.03883% ","change":"0.020020000000000003%","rankChange":58}," Dusclops           ":{"rank":" 195  ","usage":"  0.03870% ","change":"0.02975%","rankChange":113}," Probopass          ":{"rank":" 196  ","usage":"  0.03847% ","change":"-0.030199999999999998%","rankChange":-36}," Uxie               ":{"rank":" 197  ","usage":"  0.03774% ","change":"0.023680000000000003%","rankChange":71}," Quagsire           ":{"rank":" 198  ","usage":"  0.03655% ","change":"-0.01759%","rankChange":-25}," Murkrow            ":{"rank":" 199  ","usage":"  0.03601% ","change":"0.01471%","rankChange":42}," Zapdos             ":{"rank":" 200  ","usage":"  0.03561% ","change":"-0.038529999999999995%","rankChange":-51}," Haxorus            ":{"rank":" 201  ","usage":"  0.03492% ","change":"0.005829999999999998%","rankChange":15}," Turtonator         ":{"rank":" 202  ","usage":"  0.03419% ","change":"0.0178%","rankChange":55}," Ribombee           ":{"rank":" 203  ","usage":"  0.03346% ","change":"0.004509999999999997%","rankChange":15}," Komala             ":{"rank":" 204  ","usage":"  0.03244% ","change":"0.009919999999999998%","rankChange":29}," Gardevoir          ":{"rank":" 205  ","usage":"  0.03228% ","change":"-0.030009999999999995%","rankChange":-41}," Absol-Mega         ":{"rank":" 206  ","usage":"  0.03164% ","change":"-0.08128%","rankChange":-81}," Gastrodon          ":{"rank":" 207  ","usage":"  0.03129% ","change":"-0.09576%","rankChange":-86}," Thundurus-Therian  ":{"rank":" 208  ","usage":"  0.03118% ","change":"0.0092%","rankChange":29}," Golem-Alola        ":{"rank":" 209  ","usage":"  0.03049% ","change":"-0.01859%","rankChange":-25}," Xatu               ":{"rank":" 210  ","usage":"  0.03045% ","change":"0.008140000000000001%","rankChange":25}," Noivern            ":{"rank":" 211  ","usage":"  0.03006% ","change":"0.01586%","rankChange":56}," Manaphy            ":{"rank":" 212  ","usage":"  0.02974% ","change":"-0.013500000000000002%","rankChange":-21}," Zoroark            ":{"rank":" 213  ","usage":"  0.02969% ","change":"-0.07802999999999999%","rankChange":-85}," Conkeldurr         ":{"rank":" 214  ","usage":"  0.02904% ","change":"0.0006899999999999996%","rankChange":5}," Eelektross         ":{"rank":" 215  ","usage":"  0.02899% ","change":"0.013999999999999999%","rankChange":47}," Alakazam           ":{"rank":" 216  ","usage":"  0.02871% ","change":"-0.02067%","rankChange":-34}," Blastoise-Mega     ":{"rank":" 217  ","usage":"  0.02831% ","change":"-0.013430000000000001%","rankChange":-25}," Mandibuzz          ":{"rank":" 218  ","usage":"  0.02738% ","change":"-0.012799999999999999%","rankChange":-22}," Volcanion          ":{"rank":" 219  ","usage":"  0.02715% ","change":"-0.009980000000000003%","rankChange":-18}," Kingdra            ":{"rank":" 220  ","usage":"  0.02699% ","change":"-0.011840000000000003%","rankChange":-22}," Raikou             ":{"rank":" 221  ","usage":"  0.02571% ","change":"0.010320000000000001%","rankChange":39}," Crabominable       ":{"rank":" 222  ","usage":"  0.02559% ","change":"0.003640000000000001%","rankChange":16}," Persian-Alola      ":{"rank":" 223  ","usage":"  0.02557% ","change":"-0.0014900000000000017%","rankChange":-1}," Lycanroc-Midnight  ":{"rank":" 224  ","usage":"  0.02540% ","change":"-0.0009300000000000003%","rankChange":0}," Ambipom            ":{"rank":" 225  ","usage":"  0.02538% ","change":"0.01899%","rankChange":114}," Machamp            ":{"rank":" 226  ","usage":"  0.02518% ","change":"-0.015009999999999996%","rankChange":-31}," Palossand          ":{"rank":" 227  ","usage":"  0.02516% ","change":"-0.0048400000000000006%","rankChange":-16}," Pikachu            ":{"rank":" 228  ","usage":"  0.02403% ","change":"-0.009839999999999998%","rankChange":-24}," Pyroar             ":{"rank":" 229  ","usage":"  0.02395% ","change":"0.022189999999999998%","rankChange":224}," Gigalith           ":{"rank":" 230  ","usage":"  0.02383% ","change":"0.006540000000000001%","rankChange":25}," Hawlucha           ":{"rank":" 231  ","usage":"  0.02377% ","change":"0.0004699999999999982%","rankChange":0}," Weezing            ":{"rank":" 232  ","usage":"  0.02373% ","change":"0.02023%","rankChange":158}," Nosepass           ":{"rank":" 233  ","usage":"  0.02346% ","change":"-0.008259999999999997%","rankChange":-23}," Honchkrow          ":{"rank":" 234  ","usage":"  0.02323% ","change":"0.008650000000000001%","rankChange":29}," Silvally-Fairy     ":{"rank":" 235  ","usage":"  0.02246% ","change":"-0.0037199999999999976%","rankChange":-9}," Sandslash-Alola    ":{"rank":" 236  ","usage":"  0.02177% ","change":"0.00855%","rankChange":38}," Aerodactyl         ":{"rank":" 237  ","usage":"  0.02141% ","change":"0.005839999999999998%","rankChange":22}," Solrock            ":{"rank":" 238  ","usage":"  0.02138% ","change":"-0.052070000000000005%","rankChange":-88}," Nidoking           ":{"rank":" 239  ","usage":"  0.02107% ","change":"-0.0011000000000000003%","rankChange":-3}," Toucannon          ":{"rank":" 240  ","usage":"  0.02095% ","change":"0.0074800000000000005%","rankChange":32}," Glaceon            ":{"rank":" 241  ","usage":"  0.02084% ","change":"0.01272%","rankChange":77}," Sharpedo-Mega      ":{"rank":" 242  ","usage":"  0.02064% ","change":"-0.01638%","rankChange":-40}," Tyrantrum          ":{"rank":" 243  ","usage":"  0.02050% ","change":"0.011680000000000001%","rankChange":67}," Keldeo             ":{"rank":" 244  ","usage":"  0.02020% ","change":"-0.033280000000000004%","rankChange":-70}," Pelipper           ":{"rank":" 245  ","usage":"  0.01990% ","change":"-0.009419999999999998%","rankChange":-32}," Absol              ":{"rank":" 246  ","usage":"  0.01988% ","change":"0.01779%","rankChange":191}," Silvally           ":{"rank":" 247  ","usage":"  0.01934% ","change":"-0.0125%","rankChange":-38}," Masquerain         ":{"rank":" 248  ","usage":"  0.01925% ","change":"0.01034%","rankChange":61}," Doublade           ":{"rank":" 249  ","usage":"  0.01903% ","change":"0.009649999999999999%","rankChange":51}," Slurpuff           ":{"rank":" 250  ","usage":"  0.01899% ","change":"-0.00562%","rankChange":-21}," Sceptile           ":{"rank":" 251  ","usage":"  0.01896% ","change":"-0.0011699999999999974%","rankChange":-6}," Donphan            ":{"rank":" 252  ","usage":"  0.01896% ","change":"-0.0078099999999999975%","rankChange":-29}," Alomomola          ":{"rank":" 253  ","usage":"  0.01881% ","change":"0.00273%","rankChange":5}," Drampa             ":{"rank":" 254  ","usage":"  0.01849% ","change":"-0.01564%","rankChange":-51}," Slowbro            ":{"rank":" 255  ","usage":"  0.01834% ","change":"-0.002360000000000001%","rankChange":-13}," Rhyperior          ":{"rank":" 256  ","usage":"  0.01829% ","change":"0.004780000000000001%","rankChange":15}," Shaymin            ":{"rank":" 257  ","usage":"  0.01825% ","change":"0.01619%","rankChange":181}," Electivire         ":{"rank":" 258  ","usage":"  0.01728% ","change":"-0.0024199999999999985%","rankChange":-12}," Empoleon           ":{"rank":" 259  ","usage":"  0.01698% ","change":"-0.014950000000000001%","rankChange":-51}," Aron               ":{"rank":" 260  ","usage":"  0.01690% ","change":"-0.0006400000000000017%","rankChange":-6}," Accelgor           ":{"rank":" 261  ","usage":"  0.01679% ","change":"0.00251%","rankChange":5}," Type: Null         ":{"rank":" 262  ","usage":"  0.01678% ","change":"-0.0028399999999999988%","rankChange":-15}," Pinsir-Mega        ":{"rank":" 263  ","usage":"  0.01671% ","change":"-0.02349%","rankChange":-69}," Drifblim           ":{"rank":" 264  ","usage":"  0.01608% ","change":"0.01307%","rankChange":136}," Lanturn            ":{"rank":" 265  ","usage":"  0.01605% ","change":"-0.0030500000000000006%","rankChange":-16}," Entei              ":{"rank":" 266  ","usage":"  0.01600% ","change":"-0.0028800000000000006%","rankChange":-15}," Mantine            ":{"rank":" 267  ","usage":"  0.01571% ","change":"0.0023299999999999987%","rankChange":6}," Gallade            ":{"rank":" 268  ","usage":"  0.01525% ","change":"0.006659999999999999%","rankChange":46}," Dugtrio-Alola      ":{"rank":" 269  ","usage":"  0.01523% ","change":"0.00541%","rankChange":24}," Florges            ":{"rank":" 270  ","usage":"  0.01492% ","change":"0.005299999999999999%","rankChange":27}," Hippowdon          ":{"rank":" 271  ","usage":"  0.01475% ","change":"-0.001740000000000002%","rankChange":-15}," Sharpedo           ":{"rank":" 272  ","usage":"  0.01453% ","change":"0.0095%","rankChange":94}," Lapras             ":{"rank":" 273  ","usage":"  0.01446% ","change":"0.00721%","rankChange":55}," Darmanitan         ":{"rank":" 274  ","usage":"  0.01441% ","change":"0.009479999999999999%","rankChange":94}," Venomoth           ":{"rank":" 275  ","usage":"  0.01438% ","change":"-0.05775999999999999%","rankChange":-121}," Bruxish            ":{"rank":" 276  ","usage":"  0.01434% ","change":"0.00855%","rankChange":74}," Jumpluff           ":{"rank":" 277  ","usage":"  0.01406% ","change":"0.01326%","rankChange":234}," Slaking            ":{"rank":" 278  ","usage":"  0.01403% ","change":"0.00353%","rankChange":13}," Reuniclus          ":{"rank":" 279  ","usage":"  0.01402% ","change":"0.004749999999999999%","rankChange":24}," Vivillon           ":{"rank":" 280  ","usage":"  0.01381% ","change":"0.0020199999999999992%","rankChange":1}," Typhlosion         ":{"rank":" 281  ","usage":"  0.01379% ","change":"0.0023099999999999996%","rankChange":2}," Feraligatr         ":{"rank":" 282  ","usage":"  0.01338% ","change":"-0.005819999999999999%","rankChange":-34}," Sigilyph           ":{"rank":" 283  ","usage":"  0.01322% ","change":"0.0012900000000000012%","rankChange":-3}," Celebi             ":{"rank":" 284  ","usage":"  0.01310% ","change":"0.00808%","rankChange":83}," Diglett            ":{"rank":" 285  ","usage":"  0.01301% ","change":"0.012920000000000001%","rankChange":351}," Rotom-Heat         ":{"rank":" 286  ","usage":"  0.01297% ","change":"-0.01634%","rankChange":-72}," Bastiodon          ":{"rank":" 287  ","usage":"  0.01245% ","change":"0.007959999999999998%","rankChange":88}," Venusaur           ":{"rank":" 288  ","usage":"  0.01234% ","change":"-0.0016500000000000004%","rankChange":-19}," Cobalion           ":{"rank":" 289  ","usage":"  0.01231% ","change":"-0.0007600000000000003%","rankChange":-13}," Archeops           ":{"rank":" 290  ","usage":"  0.01203% ","change":"0.002660000000000001%","rankChange":11}," Liepard            ":{"rank":" 291  ","usage":"  0.01195% ","change":"0.009500000000000001%","rankChange":131}," Torkoal            ":{"rank":" 292  ","usage":"  0.01178% ","change":"-0.033010000000000005%","rankChange":-104}," Spiritomb          ":{"rank":" 293  ","usage":"  0.01134% ","change":"0.004959999999999999%","rankChange":47}," Rattata            ":{"rank":" 294  ","usage":"  0.01104% ","change":"0.0013299999999999996%","rankChange":0}," Regirock           ":{"rank":" 295  ","usage":"  0.01073% ","change":"0.00564%","rankChange":69}," Tangrowth          ":{"rank":" 296  ","usage":"  0.01061% ","change":"0.0009099999999999994%","rankChange":-1}," Ninetales          ":{"rank":" 297  ","usage":"  0.01059% ","change":"0.00578%","rankChange":72}," Lilligant          ":{"rank":" 298  ","usage":"  0.01051% ","change":"0.0062900000000000005%","rankChange":81}," Lunatone           ":{"rank":" 299  ","usage":"  0.01039% ","change":"0.01017%","rankChange":290}," Lurantis           ":{"rank":" 300  ","usage":"  0.01026% ","change":"0.00279%","rankChange":26}," Carbink            ":{"rank":" 301  ","usage":"  0.01025% ","change":"-0.01427%","rankChange":-71}," Taillow            ":{"rank":" 302  ","usage":"  0.01022% ","change":"-0.01959%","rankChange":-90}," Cofagrigus         ":{"rank":" 303  ","usage":"  0.01012% ","change":"0.0028800000000000006%","rankChange":26}," Ludicolo           ":{"rank":" 304  ","usage":"  0.01010% ","change":"0.00294%","rankChange":26}," Scrafty            ":{"rank":" 305  ","usage":"  0.00989% ","change":"0.0029%","rankChange":28}," Volbeat            ":{"rank":" 306  ","usage":"  0.00939% ","change":"-0.03997%","rankChange":-123}," Trevenant          ":{"rank":" 307  ","usage":"  0.00928% ","change":"-0.03899%","rankChange":-121}," Hitmonlee          ":{"rank":" 308  ","usage":"  0.00923% ","change":"0.00347%","rankChange":44}," Jellicent          ":{"rank":" 309  ","usage":"  0.00912% ","change":"0.0036099999999999995%","rankChange":47}," Articuno           ":{"rank":" 310  ","usage":"  0.00911% ","change":"0.00219%","rankChange":24}," Toxicroak          ":{"rank":" 311  ","usage":"  0.00905% ","change":"0.0017500000000000007%","rankChange":16}," Regice             ":{"rank":" 312  ","usage":"  0.00884% ","change":"0.0017300000000000006%","rankChange":19}," Pangoro            ":{"rank":" 313  ","usage":"  0.00871% ","change":"-0.07257000000000001%","rankChange":-173}," Torterra           ":{"rank":" 314  ","usage":"  0.00867% ","change":"0.0011800000000000005%","rankChange":11}," Roserade           ":{"rank":" 315  ","usage":"  0.00866% ","change":"-0.0032900000000000013%","rankChange":-36}," Shiinotic          ":{"rank":" 316  ","usage":"  0.00864% ","change":"0.0004299999999999998%","rankChange":1}," Cinccino           ":{"rank":" 317  ","usage":"  0.00850% ","change":"-0.005379999999999999%","rankChange":-47}," Regigigas          ":{"rank":" 318  ","usage":"  0.00843% ","change":"0.00162%","rankChange":18}," Exploud            ":{"rank":" 319  ","usage":"  0.00837% ","change":"-0.0011399999999999987%","rankChange":-20}," Aggron             ":{"rank":" 320  ","usage":"  0.00836% ","change":"0.0013599999999999992%","rankChange":12}," Braviary           ":{"rank":" 321  ","usage":"  0.00834% ","change":"0.0005000000000000004%","rankChange":0}," Rampardos          ":{"rank":" 322  ","usage":"  0.00833% ","change":"-0.06276%","rankChange":-163}," Pineco             ":{"rank":" 323  ","usage":"  0.00812% ","change":"0.0030800000000000003%","rankChange":42}," Tornadus-Therian   ":{"rank":" 324  ","usage":"  0.00808% ","change":"0.0014200000000000003%","rankChange":14}," Klinklang          ":{"rank":" 325  ","usage":"  0.00782% ","change":"0.00579%","rankChange":117}," Gorebyss           ":{"rank":" 326  ","usage":"  0.00775% ","change":"0.0025900000000000003%","rankChange":37}," Raichu             ":{"rank":" 327  ","usage":"  0.00761% ","change":"0.0033299999999999996%","rankChange":51}," Silvally-Dragon    ":{"rank":" 328  ","usage":"  0.00727% ","change":"0.006110000000000001%","rankChange":150}," Silvally-Ghost     ":{"rank":" 329  ","usage":"  0.00718% ","change":"0.00115%","rankChange":15}," Meowstic           ":{"rank":" 330  ","usage":"  0.00716% ","change":"-0.0014800000000000004%","rankChange":-18}," Mienshao           ":{"rank":" 331  ","usage":"  0.00715% ","change":"0.00421%","rankChange":73}," Silvally-Flying    ":{"rank":" 332  ","usage":"  0.00702% ","change":"0.00542%","rankChange":125}," Meloetta           ":{"rank":" 333  ","usage":"  0.00698% ","change":"0.0014400000000000003%","rankChange":21}," Oranguru           ":{"rank":" 334  ","usage":"  0.00692% ","change":"0.00418%","rankChange":80}," Luxray             ":{"rank":" 335  ","usage":"  0.00687% ","change":"-0.00236%","rankChange":-30}," Ursaring           ":{"rank":" 336  ","usage":"  0.00684% ","change":"0.00392%","rankChange":69}," Golurk             ":{"rank":" 337  ","usage":"  0.00682% ","change":"0.0029499999999999995%","rankChange":47}," Charizard          ":{"rank":" 338  ","usage":"  0.00655% ","change":"-0.02155%","rankChange":-117}," Steelix            ":{"rank":" 339  ","usage":"  0.00655% ","change":"-0.004449999999999999%","rankChange":-52}," Politoed           ":{"rank":" 340  ","usage":"  0.00650% ","change":"-0.00317%","rankChange":-44}," Chesnaught         ":{"rank":" 341  ","usage":"  0.00647% ","change":"-0.00621%","rankChange":-64}," Malamar            ":{"rank":" 342  ","usage":"  0.00614% ","change":"-0.00443%","rankChange":-52}," Magikarp           ":{"rank":" 343  ","usage":"  0.00588% ","change":"0.00245%","rankChange":49}," Delphox            ":{"rank":" 344  ","usage":"  0.00571% ","change":"-0.00884%","rankChange":-80}," Golduck            ":{"rank":" 345  ","usage":"  0.00570% ","change":"-0.02348%","rankChange":-130}," Magmortar          ":{"rank":" 346  ","usage":"  0.00569% ","change":"-0.00007000000000000062%","rankChange":5}," Swellow            ":{"rank":" 347  ","usage":"  0.00565% ","change":"-0.01278%","rankChange":-94}," Silvally-Fire      ":{"rank":" 348  ","usage":"  0.00555% ","change":"0.00266%","rankChange":60}," Silvally-Water     ":{"rank":" 349  ","usage":"  0.00555% ","change":"0.00457%","rankChange":148}," Heracross          ":{"rank":" 350  ","usage":"  0.00552% ","change":"-0.00296%","rankChange":-34}," Silvally-Grass     ":{"rank":" 351  ","usage":"  0.00532% ","change":"0.00392%","rankChange":118}," Blastoise          ":{"rank":" 352  ","usage":"  0.00528% ","change":"-0.01631%","rankChange":-113}," Togedemaru         ":{"rank":" 353  ","usage":"  0.00524% ","change":"-0.00733%","rankChange":-75}," Omastar            ":{"rank":" 354  ","usage":"  0.00522% ","change":"0.00149%","rankChange":34}," Swoobat            ":{"rank":" 355  ","usage":"  0.00514% ","change":"0.0026899999999999997%","rankChange":68}," Leafeon            ":{"rank":" 356  ","usage":"  0.00513% ","change":"-0.0015399999999999997%","rankChange":-19}," Tauros             ":{"rank":" 357  ","usage":"  0.00512% ","change":"0.0024500000000000004%","rankChange":58}," Diggersby          ":{"rank":" 358  ","usage":"  0.00503% ","change":"-0.00253%","rankChange":-35}," Emolga             ":{"rank":" 359  ","usage":"  0.00500% ","change":"-0.004299999999999999%","rankChange":-57}," Mismagius          ":{"rank":" 360  ","usage":"  0.00500% ","change":"0.00219%","rankChange":49}," Feebas             ":{"rank":" 361  ","usage":"  0.00497% ","change":"0.0049499999999999995%","rankChange":339}," Registeel          ":{"rank":" 362  ","usage":"  0.00491% ","change":"-0.006689999999999999%","rankChange":-80}," Hariyama           ":{"rank":" 363  ","usage":"  0.00491% ","change":"-0.0036999999999999993%","rankChange":-50}," Cradily            ":{"rank":" 364  ","usage":"  0.00482% ","change":"-0.00652%","rankChange":-80}," Vanilluxe          ":{"rank":" 365  ","usage":"  0.00480% ","change":"0.0028899999999999993%","rankChange":83}," Silvally-Electric  ":{"rank":" 366  ","usage":"  0.00478% ","change":"0.0013700000000000006%","rankChange":28}," Flareon            ":{"rank":" 367  ","usage":"  0.00477% ","change":"-0.00482%","rankChange":-69}," Heliolisk          ":{"rank":" 368  ","usage":"  0.00461% ","change":"-0.004639999999999999%","rankChange":-64}," Hoopa              ":{"rank":" 369  ","usage":"  0.00445% ","change":"-0.01458%","rankChange":-119}," Moltres            ":{"rank":" 370  ","usage":"  0.00438% ","change":"-0.0014299999999999998%","rankChange":-21}," Crawdaunt          ":{"rank":" 371  ","usage":"  0.00438% ","change":"-0.0011399999999999995%","rankChange":-16}," Kecleon            ":{"rank":" 372  ","usage":"  0.00436% ","change":"0.00287%","rankChange":91}," Audino             ":{"rank":" 373  ","usage":"  0.00435% ","change":"0.00394%","rankChange":173}," Abomasnow          ":{"rank":" 374  ","usage":"  0.00432% ","change":"0.00254%","rankChange":77}," Seismitoad         ":{"rank":" 375  ","usage":"  0.00421% ","change":"0.00017%","rankChange":7}," Passimian          ":{"rank":" 376  ","usage":"  0.00419% ","change":"0.00039000000000000016%","rankChange":10}," Medicham           ":{"rank":" 377  ","usage":"  0.00405% ","change":"0.0012599999999999998%","rankChange":35}," Poliwrath          ":{"rank":" 378  ","usage":"  0.00403% ","change":"0.0030299999999999997%","rankChange":114}," Silvally-Dark      ":{"rank":" 379  ","usage":"  0.00392% ","change":"0.00341%","rankChange":158}," Rattata-Alola      ":{"rank":" 380  ","usage":"  0.00383% ","change":"0.00235%","rankChange":86}," Stoutland          ":{"rank":" 381  ","usage":"  0.00381% ","change":"0.00316%","rankChange":139}," Yanmega            ":{"rank":" 382  ","usage":"  0.00380% ","change":"-0.00306%","rankChange":-47}," Beautifly          ":{"rank":" 383  ","usage":"  0.00367% ","change":"0.00354%","rankChange":232}," Dragalge           ":{"rank":" 384  ","usage":"  0.00361% ","change":"0.00067%","rankChange":19}," Rhydon             ":{"rank":" 385  ","usage":"  0.00355% ","change":"0.00011000000000000029%","rankChange":6}," Slowking           ":{"rank":" 386  ","usage":"  0.00354% ","change":"-0.004360000000000001%","rankChange":-66}," Exeggutor          ":{"rank":" 387  ","usage":"  0.00350% ","change":"-0.0012499999999999998%","rankChange":-16}," Dusknoir           ":{"rank":" 388  ","usage":"  0.00345% ","change":"-0.00519%","rankChange":-77}," Gumshoos           ":{"rank":" 389  ","usage":"  0.00344% ","change":"0.00251%","rankChange":114}," Kabutops           ":{"rank":" 390  ","usage":"  0.00342% ","change":"-0.00566%","rankChange":-83}," Hitmontop          ":{"rank":" 391  ","usage":"  0.00335% ","change":"-0.0010500000000000002%","rankChange":-14}," Qwilfish           ":{"rank":" 392  ","usage":"  0.00333% ","change":"-0.00796%","rankChange":-107}," Escavalier         ":{"rank":" 393  ","usage":"  0.00322% ","change":"0.0009100000000000002%","rankChange":37}," Lickilicky         ":{"rank":" 394  ","usage":"  0.00317% ","change":"0.00011000000000000029%","rankChange":5}," Linoone            ":{"rank":" 395  ","usage":"  0.00316% ","change":"0.0009000000000000002%","rankChange":37}," Houndoom           ":{"rank":" 396  ","usage":"  0.00315% ","change":"-0.00223%","rankChange":-38}," Magnemite          ":{"rank":" 397  ","usage":"  0.00307% ","change":"-0.00784%","rankChange":-109}," Leavanny           ":{"rank":" 398  ","usage":"  0.00301% ","change":"-0.05692%","rankChange":-231}," Armaldo            ":{"rank":" 399  ","usage":"  0.00300% ","change":"0.00217%","rankChange":110}," Carracosta         ":{"rank":" 400  ","usage":"  0.00297% ","change":"-0.0022400000000000002%","rankChange":-38}," Golem              ":{"rank":" 401  ","usage":"  0.00295% ","change":"-0.0023400000000000005%","rankChange":-41}," Tangela            ":{"rank":" 402  ","usage":"  0.00285% ","change":"0.00119%","rankChange":53}," Beartic            ":{"rank":" 403  ","usage":"  0.00283% ","change":"0.00172%","rankChange":80}," Silvally-Ground    ":{"rank":" 404  ","usage":"  0.00283% ","change":"-0.0009199999999999998%","rankChange":-17}," Silvally-Steel     ":{"rank":" 405  ","usage":"  0.00276% ","change":"-0.0048000000000000004%","rankChange":-81}," Victreebel         ":{"rank":" 406  ","usage":"  0.00273% ","change":"0.00013999999999999993%","rankChange":12}," Ampharos           ":{"rank":" 407  ","usage":"  0.00266% ","change":"-0.0018199999999999996%","rankChange":-31}," Kangaskhan         ":{"rank":" 408  ","usage":"  0.00264% ","change":"0.00165%","rankChange":86}," Crustle            ":{"rank":" 409  ","usage":"  0.00254% ","change":"-0.00849%","rankChange":-123}," Virizion           ":{"rank":" 410  ","usage":"  0.00251% ","change":"0.0012900000000000001%","rankChange":67}," Chatot             ":{"rank":" 411  ","usage":"  0.00250% ","change":"-0.01194%","rankChange":-146}," Emboar             ":{"rank":" 412  ","usage":"  0.00246% ","change":"-0.006659999999999999%","rankChange":-106}," Wailord            ":{"rank":" 413  ","usage":"  0.00239% ","change":"0.0009000000000000002%","rankChange":51}," Pidgeot            ":{"rank":" 414  ","usage":"  0.00238% ","change":"-0.00014999999999999996%","rankChange":7}," Marowak            ":{"rank":" 415  ","usage":"  0.00238% ","change":"-0.01998%","rankChange":-181}," Rotom-Mow          ":{"rank":" 416  ","usage":"  0.00235% ","change":"0.00107%","rankChange":58}," Huntail            ":{"rank":" 417  ","usage":"  0.00231% ","change":"-0.00239%","rankChange":-45}," Samurott           ":{"rank":" 418  ","usage":"  0.00231% ","change":"-0.0024700000000000004%","rankChange":-48}," Tropius            ":{"rank":" 419  ","usage":"  0.00231% ","change":"0.00191%","rankChange":128}," Miltank            ":{"rank":" 420  ","usage":"  0.00227% ","change":"-0.0036600000000000005%","rankChange":-73}," Ferroseed          ":{"rank":" 421  ","usage":"  0.00221% ","change":"-0.01098%","rankChange":-146}," Oricorio-Pom-Pom   ":{"rank":" 422  ","usage":"  0.00220% ","change":"-0.00023999999999999976%","rankChange":2}," Electrode          ":{"rank":" 423  ","usage":"  0.00213% ","change":"-0.00169%","rankChange":-38}," Floatzel           ":{"rank":" 424  ","usage":"  0.00212% ","change":"-0.0004100000000000002%","rankChange":-4}," Swalot             ":{"rank":" 425  ","usage":"  0.00211% ","change":"0.00202%","rankChange":206}," Carnivine          ":{"rank":" 426  ","usage":"  0.00209% ","change":"0.0020199999999999997%","rankChange":215}," Gothorita          ":{"rank":" 427  ","usage":"  0.00207% ","change":"-0.0011200000000000003%","rankChange":-29}," Stunfisk           ":{"rank":" 428  ","usage":"  0.00206% ","change":"0.0009100000000000002%","rankChange":53}," Wigglytuff         ":{"rank":" 429  ","usage":"  0.00205% ","change":"-0.0031899999999999997%","rankChange":-68}," Basculin           ":{"rank":" 430  ","usage":"  0.00204% ","change":"0.00161%","rankChange":114}," Unfezant           ":{"rank":" 431  ","usage":"  0.00200% ","change":"0.00147%","rankChange":102}," Zorua              ":{"rank":" 432  ","usage":"  0.00200% ","change":"0.00161%","rankChange":118}," Kyurem             ":{"rank":" 433  ","usage":"  0.00186% ","change":"-0.00815%","rankChange":-141}," Muk                ":{"rank":" 434  ","usage":"  0.00184% ","change":"-0.0005799999999999998%","rankChange":-9}," Oricorio-Sensu     ":{"rank":" 435  ","usage":"  0.00183% ","change":"0.00131%","rankChange":100}," Caterpie           ":{"rank":" 436  ","usage":"  0.00181% ","change":"0.00157%","rankChange":148}," Silvally-Bug       ":{"rank":" 437  ","usage":"  0.00173% ","change":"0.00147%","rankChange":143}," Meganium           ":{"rank":" 438  ","usage":"  0.00171% ","change":"-0.0005399999999999999%","rankChange":-4}," Rapidash           ":{"rank":" 439  ","usage":"  0.00166% ","change":"0.0006000000000000001%","rankChange":47}," Lopunny            ":{"rank":" 440  ","usage":"  0.00162% ","change":"-0.00928%","rankChange":-151}," Silvally-Psychic   ":{"rank":" 441  ","usage":"  0.00162% ","change":"0.0014399999999999999%","rankChange":159}," Oricorio           ":{"rank":" 442  ","usage":"  0.00158% ","change":"0.00043000000000000004%","rankChange":37}," Wynaut             ":{"rank":" 443  ","usage":"  0.00157% ","change":"0.0010400000000000001%","rankChange":91}," Primeape           ":{"rank":" 444  ","usage":"  0.00157% ","change":"0.00095%","rankChange":82}," Druddigon          ":{"rank":" 445  ","usage":"  0.00156% ","change":"-0.00124%","rankChange":-34}," Barbaracle         ":{"rank":" 446  ","usage":"  0.00155% ","change":"-0.00611%","rankChange":-124}," Clawitzer          ":{"rank":" 447  ","usage":"  0.00154% ","change":"-0.00466%","rankChange":-105}," Silvally-Poison    ":{"rank":" 448  ","usage":"  0.00152% ","change":"-0.0046300000000000004%","rankChange":-105}," Magneton           ":{"rank":" 449  ","usage":"  0.00150% ","change":"-0.00043000000000000004%","rankChange":-2}," Altaria            ":{"rank":" 450  ","usage":"  0.00149% ","change":"-0.00258%","rankChange":-69}," Shiftry            ":{"rank":" 451  ","usage":"  0.00149% ","change":"0.00117%","rankChange":107}," Noctowl            ":{"rank":" 452  ","usage":"  0.00147% ","change":"-0.00084%","rankChange":-24}," Aurorus            ":{"rank":" 453  ","usage":"  0.00145% ","change":"-0.00181%","rankChange":-56}," Silvally-Fighting  ":{"rank":" 454  ","usage":"  0.00143% ","change":"0.0006000000000000001%","rankChange":54}," Arbok              ":{"rank":" 455  ","usage":"  0.00140% ","change":"-0.00018000000000000004%","rankChange":3}," Hitmonchan         ":{"rank":" 456  ","usage":"  0.00138% ","change":"-0.00454%","rankChange":-108}," Fearow             ":{"rank":" 457  ","usage":"  0.00138% ","change":"0.00038999999999999994%","rankChange":39}," Delibird           ":{"rank":" 458  ","usage":"  0.00136% ","change":"0.0008700000000000001%","rankChange":81}," Silvally-Ice       ":{"rank":" 459  ","usage":"  0.00134% ","change":"-0.000020000000000000052%","rankChange":11}," Pachirisu          ":{"rank":" 460  ","usage":"  0.00133% ","change":"0.00027000000000000006%","rankChange":25}," Zebstrika          ":{"rank":" 461  ","usage":"  0.00128% ","change":"0.0005600000000000001%","rankChange":55}," Munchlax           ":{"rank":" 462  ","usage":"  0.00128% ","change":"-0.00428%","rankChange":-109}," Golbat             ":{"rank":" 463  ","usage":"  0.00124% ","change":"0.00035000000000000005%","rankChange":43}," Gogoat             ":{"rank":" 464  ","usage":"  0.00120% ","change":"-0.00177%","rankChange":-62}," Mawile             ":{"rank":" 465  ","usage":"  0.00112% ","change":"-0.00115%","rankChange":-34}," Raticate           ":{"rank":" 466  ","usage":"  0.00109% ","change":"0.00042%","rankChange":53}," Scyther            ":{"rank":" 467  ","usage":"  0.00107% ","change":"-0.0035400000000000006%","rankChange":-93}," Raticate-Alola     ":{"rank":" 468  ","usage":"  0.00107% ","change":"-0.00158%","rankChange":-51}," Illumise           ":{"rank":" 469  ","usage":"  0.00105% ","change":"0.00039999999999999996%","rankChange":52}," Lileep             ":{"rank":" 470  ","usage":"  0.00105% ","change":"0.0009%","rankChange":138}," Kirlia             ":{"rank":" 471  ","usage":"  0.00105% ","change":"0.001%","rankChange":184}," Cryogonal          ":{"rank":" 472  ","usage":"  0.00105% ","change":"-0.00161%","rankChange":-56}," Manectric          ":{"rank":" 473  ","usage":"  0.00104% ","change":"-0.00268%","rankChange":-84}," Walrein            ":{"rank":" 474  ","usage":"  0.00103% ","change":"-0.00102%","rankChange":-34}," Starly             ":{"rank":" 475  ","usage":"  0.00096% ","change":"0.000010000000000000026%","rankChange":27}," Piloswine          ":{"rank":" 476  ","usage":"  0.00088% ","change":"0.0007300000000000001%","rankChange":134}," Porygon            ":{"rank":" 477  ","usage":"  0.00087% ","change":"0.00069%","rankChange":122}," Sudowoodo          ":{"rank":" 478  ","usage":"  0.00087% ","change":"-0.00028%","rankChange":2}," Spinda             ":{"rank":" 479  ","usage":"  0.00087% ","change":"0.00063%","rankChange":106}," Electabuzz         ":{"rank":" 480  ","usage":"  0.00080% ","change":"-0.00088%","rankChange":-26}," Furfrou            ":{"rank":" 481  ","usage":"  0.00079% ","change":"-0.00198%","rankChange":-68}," Squirtle           ":{"rank":" 482  ","usage":"  0.00077% ","change":"0.0006%","rankChange":121}," Bulbasaur          ":{"rank":" 483  ","usage":"  0.00075% ","change":"0.00065%","rankChange":142}," Sandygast          ":{"rank":" 484  ","usage":"  0.00074% ","change":"0.00073%","rankChange":232}," Dunsparce          ":{"rank":" 485  ","usage":"  0.00074% ","change":"-0.00157%","rankChange":-56}," Staryu             ":{"rank":" 486  ","usage":"  0.00071% ","change":"0.00049%","rankChange":106}," Gourgeist-Super    ":{"rank":" 487  ","usage":"  0.00071% ","change":"-0.0010899999999999998%","rankChange":-38}," Carvanha           ":{"rank":" 488  ","usage":"  0.00071% ","change":"0.00037%","rankChange":69}," Dedenne            ":{"rank":" 489  ","usage":"  0.00071% ","change":"-0.0012200000000000002%","rankChange":-43}," Mesprit            ":{"rank":" 490  ","usage":"  0.00070% ","change":"-0.00009000000000000002%","rankChange":23}," Rotom-Frost        ":{"rank":" 491  ","usage":"  0.00070% ","change":"0.00047999999999999996%","rankChange":99}," Hypno              ":{"rank":" 492  ","usage":"  0.00068% ","change":"-0.00011999999999999999%","rankChange":18}," Cacturne           ":{"rank":" 493  ","usage":"  0.00065% ","change":"-0.0017499999999999998%","rankChange":-67}," Boldore            ":{"rank":" 494  ","usage":"  0.00064% ","change":"0.0005600000000000001%","rankChange":146}," Skuntank           ":{"rank":" 495  ","usage":"  0.00064% ","change":"-0.0006%","rankChange":-19}," Persian            ":{"rank":" 496  ","usage":"  0.00063% ","change":"0.00006000000000000005%","rankChange":34}," Dodrio             ":{"rank":" 497  ","usage":"  0.00062% ","change":"-0.0022700000000000003%","rankChange":-90}," Minun              ":{"rank":" 498  ","usage":"  0.00061% ","change":"0.0005899999999999999%","rankChange":203}," Butterfree         ":{"rank":" 499  ","usage":"  0.00061% ","change":"-0.00095%","rankChange":-39}," Cutiefly           ":{"rank":" 500  ","usage":"  0.00060% ","change":"0.00049%","rankChange":119}," Mothim             ":{"rank":" 501  ","usage":"  0.00059% ","change":"-0.00118%","rankChange":-49}," Vullaby            ":{"rank":" 502  ","usage":"  0.00058% ","change":"-0.00028%","rankChange":5}," Nidoqueen          ":{"rank":" 503  ","usage":"  0.00054% ","change":"-0.0057%","rankChange":-162}," Camerupt           ":{"rank":" 504  ","usage":"  0.00052% ","change":"-0.00053%","rankChange":-17}," Vespiquen          ":{"rank":" 505  ","usage":"  0.00050% ","change":"0.00015000000000000001%","rankChange":51}," Rowlet             ":{"rank":" 506  ","usage":"  0.00050% ","change":"-0.00041%","rankChange":-2}," Shieldon           ":{"rank":" 507  ","usage":"  0.00048% ","change":"0.00048%","rankChange":267}," Togetic            ":{"rank":" 508  ","usage":"  0.00045% ","change":"-0.0005800000000000001%","rankChange":-18}," Mightyena          ":{"rank":" 509  ","usage":"  0.00045% ","change":"-0.00097%","rankChange":-42}," Seaking            ":{"rank":" 510  ","usage":"  0.00043% ","change":"0.00026999999999999995%","rankChange":96}," Dragonair          ":{"rank":" 511  ","usage":"  0.00040% ","change":"-0.0017900000000000001%","rankChange":-76}," Cosmog             ":{"rank":" 512  ","usage":"  0.00039% ","change":"-0.00014%","rankChange":20}," Cubone             ":{"rank":" 513  ","usage":"  0.00037% ","change":"0.00035999999999999997%","rankChange":194}," Weedle             ":{"rank":" 514  ","usage":"  0.00036% ","change":"0.00034%","rankChange":184}," Vileplume          ":{"rank":" 515  ","usage":"  0.00036% ","change":"-0.0011899999999999999%","rankChange":-54}," Musharna           ":{"rank":" 516  ","usage":"  0.00036% ","change":"-0.0009299999999999998%","rankChange":-43}," Castform           ":{"rank":" 517  ","usage":"  0.00036% ","change":"0.00026000000000000003%","rankChange":113}," Bibarel            ":{"rank":" 518  ","usage":"  0.00036% ","change":"-0.00264%","rankChange":-117}," Litten             ":{"rank":" 519  ","usage":"  0.00036% ","change":"0.00033%","rankChange":161}," Rockruff           ":{"rank":" 520  ","usage":"  0.00036% ","change":"-0.00178%","rankChange":-84}," Pinsir             ":{"rank":" 521  ","usage":"  0.00035% ","change":"-0.0006399999999999999%","rankChange":-28}," Zangoose           ":{"rank":" 522  ","usage":"  0.00035% ","change":"-0.00292%","rankChange":-126}," Patrat             ":{"rank":" 523  ","usage":"  0.00034% ","change":"0.00034%","rankChange":298}," Kingler            ":{"rank":" 524  ","usage":"  0.00034% ","change":"-0.00093%","rankChange":-49}," Sunflora           ":{"rank":" 525  ","usage":"  0.00034% ","change":"0.00006000000000000005%","rankChange":51}," Quilava            ":{"rank":" 526  ","usage":"  0.00033% ","change":"0.00031999999999999997%","rankChange":197}," Beedrill           ":{"rank":" 527  ","usage":"  0.00032% ","change":"-0.00044999999999999993%","rankChange":-13}," Rotom              ":{"rank":" 528  ","usage":"  0.00031% ","change":"-0.00032%","rankChange":-4}," Glalie             ":{"rank":" 529  ","usage":"  0.00031% ","change":"-0.00007000000000000002%","rankChange":23}," Bidoof             ":{"rank":" 530  ","usage":"  0.00030% ","change":"0.00020999999999999995%","rankChange":104}," Charjabug          ":{"rank":" 531  ","usage":"  0.00030% ","change":"-0.00024000000000000003%","rankChange":0}," Granbull           ":{"rank":" 532  ","usage":"  0.00030% ","change":"-0.0016400000000000002%","rankChange":-88}," Riolu              ":{"rank":" 533  ","usage":"  0.00030% ","change":"-0.0015%","rankChange":-83}," Dewott             ":{"rank":" 534  ","usage":"  0.00029% ","change":"0.00028%","rankChange":197}," Garbodor           ":{"rank":" 535  ","usage":"  0.00029% ","change":"-0.00197%","rankChange":-102}," Dustox             ":{"rank":" 536  ","usage":"  0.00027% ","change":"-0.00019999999999999998%","rankChange":5}," Shellos            ":{"rank":" 537  ","usage":"  0.00027% ","change":"0%","rankChange":42}," Jynx               ":{"rank":" 538  ","usage":"  0.00026% ","change":"-0.07117%","rankChange":-381}," Cacnea             ":{"rank":" 539  ","usage":"  0.00025% ","change":"0.00014%","rankChange":82}," Chimchar           ":{"rank":" 540  ","usage":"  0.00024% ","change":"0.0002%","rankChange":129}," Hakamo-o           ":{"rank":" 541  ","usage":"  0.00024% ","change":"0.00022%","rankChange":149}," Monferno           ":{"rank":" 542  ","usage":"  0.00023% ","change":"-0.0057399999999999994%","rankChange":-197}," Pichu              ":{"rank":" 543  ","usage":"  0.00022% ","change":"-0.00007%","rankChange":26}," Combusken          ":{"rank":" 544  ","usage":"  0.00022% ","change":"-0.0009199999999999999%","rankChange":-62}," Metang             ":{"rank":" 545  ","usage":"  0.00022% ","change":"-0.00378%","rankChange":-162}," Misdreavus         ":{"rank":" 546  ","usage":"  0.00022% ","change":"0.00022%","rankChange":198}," Treecko            ":{"rank":" 547  ","usage":"  0.00022% ","change":"0.00011%","rankChange":73}," Simipour           ":{"rank":" 548  ","usage":"  0.00021% ","change":"-0.000019999999999999998%","rankChange":38}," Salandit           ":{"rank":" 549  ","usage":"  0.00021% ","change":"0.00014000000000000001%","rankChange":93}," Torracat           ":{"rank":" 550  ","usage":"  0.00021% ","change":"-0.000039999999999999996%","rankChange":31}," Amaura             ":{"rank":" 551  ","usage":"  0.00019% ","change":"0.00013000000000000002%","rankChange":94}," Magcargo           ":{"rank":" 552  ","usage":"  0.00019% ","change":"-0.0006100000000000001%","rankChange":-40}," Gurdurr            ":{"rank":" 553  ","usage":"  0.00019% ","change":"0.00018%","rankChange":153}," Scraggy            ":{"rank":" 554  ","usage":"  0.00018% ","change":"-0.00011999999999999996%","rankChange":11}," Tornadus           ":{"rank":" 555  ","usage":"  0.00017% ","change":"-0.01518%","rankChange":-294}," Torchic            ":{"rank":" 556  ","usage":"  0.00017% ","change":"0.00011000000000000002%","rankChange":96}," Staravia           ":{"rank":" 557  ","usage":"  0.00017% ","change":"0.00006000000000000001%","rankChange":65}," Ducklett           ":{"rank":" 558  ","usage":"  0.00016% ","change":"0.00016%","rankChange":307}," Bouffalant         ":{"rank":" 559  ","usage":"  0.00016% ","change":"-0.00054%","rankChange":-42}," Haunter            ":{"rank":" 560  ","usage":"  0.00016% ","change":"-0.00026999999999999995%","rankChange":-18}," Banette            ":{"rank":" 561  ","usage":"  0.00016% ","change":"-0.00057%","rankChange":-46}," Chimecho           ":{"rank":" 562  ","usage":"  0.00016% ","change":"-0.0008799999999999999%","rankChange":-74}," Braixen            ":{"rank":" 563  ","usage":"  0.00015% ","change":"0.000019999999999999998%","rankChange":50}," Watchog            ":{"rank":" 564  ","usage":"  0.00015% ","change":"-0.000040000000000000024%","rankChange":33}," Solosis            ":{"rank":" 565  ","usage":"  0.00015% ","change":"0.00015%","rankChange":232}," Archen             ":{"rank":" 566  ","usage":"  0.00015% ","change":"-0.0008200000000000001%","rankChange":-67}," Sawsbuck           ":{"rank":" 567  ","usage":"  0.00014% ","change":"0.00005999999999999998%","rankChange":70}," Spinarak           ":{"rank":" 568  ","usage":"  0.00014% ","change":"0.00010999999999999999%","rankChange":108}," Seviper            ":{"rank":" 569  ","usage":"  0.00014% ","change":"-0.00005000000000000002%","rankChange":26}," Corsola            ":{"rank":" 570  ","usage":"  0.00014% ","change":"-0.00008000000000000002%","rankChange":23}," Kricketune         ":{"rank":" 571  ","usage":"  0.00014% ","change":"-0.00009000000000000002%","rankChange":16}," Snivy              ":{"rank":" 572  ","usage":"  0.00014% ","change":"0.00013%","rankChange":140}," Vigoroth           ":{"rank":" 573  ","usage":"  0.00014% ","change":"0.00013%","rankChange":151}," Simisage           ":{"rank":" 574  ","usage":"  0.00013% ","change":"-0.00024%","rankChange":-21}," Bayleef            ":{"rank":" 575  ","usage":"  0.00013% ","change":"-0.00077%","rankChange":-70}," Froakie            ":{"rank":" 576  ","usage":"  0.00013% ","change":"0.00011999999999999999%","rankChange":137}," Totodile           ":{"rank":" 577  ","usage":"  0.00013% ","change":"0.00011999999999999999%","rankChange":137}," Vulpix-Alola       ":{"rank":" 578  ","usage":"  0.00013% ","change":"-0.00037%","rankChange":-40}," Cosmoem            ":{"rank":" 579  ","usage":"  0.00013% ","change":"-0.00052%","rankChange":-57}," Clefairy           ":{"rank":" 580  ","usage":"  0.00012% ","change":"0%","rankChange":38}," Mareanie           ":{"rank":" 581  ","usage":"  0.00012% ","change":"0.00011%","rankChange":128}," Unown              ":{"rank":" 582  ","usage":"  0.00012% ","change":"0.00011%","rankChange":128}," Yanma              ":{"rank":" 583  ","usage":"  0.00011% ","change":"0.00011%","rankChange":271}," Togepi             ":{"rank":" 584  ","usage":"  0.00011% ","change":"-0.00014%","rankChange":-1}," Girafarig          ":{"rank":" 585  ","usage":"  0.00011% ","change":"-0.00018999999999999996%","rankChange":-18}," Furret             ":{"rank":" 586  ","usage":"  0.00011% ","change":"-0.00192%","rankChange":-145}," Tirtouga           ":{"rank":" 587  ","usage":"  0.00010% ","change":"0.0001%","rankChange":309}," Aromatisse         ":{"rank":" 588  ","usage":"  0.00010% ","change":"-0.00141%","rankChange":-126}," Ivysaur            ":{"rank":" 589  ","usage":"  0.00010% ","change":"0.000019999999999999998%","rankChange":49}," Shinx              ":{"rank":" 590  ","usage":"  0.00010% ","change":"0.0001%","rankChange":225}," Dartrix            ":{"rank":" 591  ","usage":"  0.00010% ","change":"-0.00030000000000000003%","rankChange":-43}," Seadra             ":{"rank":" 592  ","usage":"  0.00009% ","change":"-0.00008%","rankChange":9}," Gourgeist          ":{"rank":" 593  ","usage":"  0.00009% ","change":"0.00004%","rankChange":63}," Charmander         ":{"rank":" 594  ","usage":"  0.00009% ","change":"0.000030000000000000004%","rankChange":54}," Cranidos           ":{"rank":" 595  ","usage":"  0.00009% ","change":"0.00009%","rankChange":279}," Whiscash           ":{"rank":" 596  ","usage":"  0.00009% ","change":"-0.00033%","rankChange":-51}," Beheeyem           ":{"rank":" 597  ","usage":"  0.00009% ","change":"-0.00005999999999999998%","rankChange":12}," Oricorio-Pa'u      ":{"rank":" 598  ","usage":"  0.00008% ","change":"-0.00004999999999999998%","rankChange":16}," Numel              ":{"rank":" 599  ","usage":"  0.00008% ","change":"0.00006000000000000001%","rankChange":104}," Cherrim            ":{"rank":" 600  ","usage":"  0.00008% ","change":"-0.00019999999999999998%","rankChange":-26}," Luvdisc            ":{"rank":" 601  ","usage":"  0.00008% ","change":"0.00008%","rankChange":275}," Gastly             ":{"rank":" 602  ","usage":"  0.00007% ","change":"-0.00125%","rankChange":-130}," Joltik             ":{"rank":" 603  ","usage":"  0.00007% ","change":"0.00007%","rankChange":256}," Sandslash          ":{"rank":" 604  ","usage":"  0.00007% ","change":"-0.00020999999999999998%","rankChange":-29}," Pikipek            ":{"rank":" 605  ","usage":"  0.00007% ","change":"-0.000020000000000000012%","rankChange":30}," Fraxure            ":{"rank":" 606  ","usage":"  0.00006% ","change":"0.00006%","rankChange":221}," Drifloon           ":{"rank":" 607  ","usage":"  0.00006% ","change":"0.00006%","rankChange":186}," Gligar             ":{"rank":" 608  ","usage":"  0.00006% ","change":"-0.00528%","rankChange":-249}," Phione             ":{"rank":" 609  ","usage":"  0.00006% ","change":"0.000009999999999999999%","rankChange":54}," Parasect           ":{"rank":" 610  ","usage":"  0.00006% ","change":"-0.00098%","rankChange":-121}," Bonsly             ":{"rank":" 611  ","usage":"  0.00006% ","change":"0.00006%","rankChange":189}," Rotom-Fan          ":{"rank":" 612  ","usage":"  0.00006% ","change":"-0.0018800000000000002%","rankChange":-167}," Swanna             ":{"rank":" 613  ","usage":"  0.00006% ","change":"0%","rankChange":36}," Slowpoke           ":{"rank":" 614  ","usage":"  0.00006% ","change":"0.00006%","rankChange":150}," Wartortle          ":{"rank":" 615  ","usage":"  0.00005% ","change":"-0.0033699999999999997%","rankChange":-222}," Pumpkaboo          ":{"rank":" 616  ","usage":"  0.00005% ","change":"0.00003%","rankChange":83}," Wormadam-Trash     ":{"rank":" 617  ","usage":"  0.00005% ","change":"0.00005%","rankChange":125}," Roselia            ":{"rank":" 618  ","usage":"  0.00005% ","change":"0.00004%","rankChange":101}," Sunkern            ":{"rank":" 619  ","usage":"  0.00005% ","change":"-0.00012000000000000002%","rankChange":-17}," Graveler           ":{"rank":" 620  ","usage":"  0.00005% ","change":"0.00004%","rankChange":98}," Magmar             ":{"rank":" 621  ","usage":"  0.00005% ","change":"-0.00058%","rankChange":-98}," Mudbray            ":{"rank":" 622  ","usage":"  0.00005% ","change":"-0.00026%","rankChange":-62}," Farfetch'd         ":{"rank":" 623  ","usage":"  0.00005% ","change":"-0.00097%","rankChange":-132}," Pidgeotto          ":{"rank":" 624  ","usage":"  0.00004% ","change":"-0.00026%","rankChange":-61}," Bellossom          ":{"rank":" 625  ","usage":"  0.00004% ","change":"-0.00023%","rankChange":-47}," Sentret            ":{"rank":" 626  ","usage":"  0.00004% ","change":"0.00004%","rankChange":203}," Machoke            ":{"rank":" 627  ","usage":"  0.00004% ","change":"0.000030000000000000004%","rankChange":106}," Voltorb            ":{"rank":" 628  ","usage":"  0.00004% ","change":"0.00004%","rankChange":211}," Onix               ":{"rank":" 629  ","usage":"  0.00004% ","change":"-0.00228%","rankChange":-202}," Metapod            ":{"rank":" 630  ","usage":"  0.00004% ","change":"-0.00012000000000000002%","rankChange":-25}," Wormadam-Sandy     ":{"rank":" 631  ","usage":"  0.00004% ","change":"0.000010000000000000003%","rankChange":40}," Shelgon            ":{"rank":" 632  ","usage":"  0.00004% ","change":"0.00002%","rankChange":64}," Ralts              ":{"rank":" 633  ","usage":"  0.00004% ","change":"0.00004%","rankChange":123}," Hippopotas         ":{"rank":" 634  ","usage":"  0.00004% ","change":"-0.00137%","rankChange":-166}," Stantler           ":{"rank":" 635  ","usage":"  0.00004% ","change":"-0.00006%","rankChange":-11}," Swinub             ":{"rank":" 636  ","usage":"  0.00004% ","change":"0.00004%","rankChange":232}," Wooper             ":{"rank":" 637  ","usage":"  0.00004% ","change":"0.00004%","rankChange":188}," Plusle             ":{"rank":" 638  ","usage":"  0.00004% ","change":"-0.000019999999999999998%","rankChange":13}," Fletchinder        ":{"rank":" 639  ","usage":"  0.00004% ","change":"-0.00005%","rankChange":-7}," Marill             ":{"rank":" 640  ","usage":"  0.00004% ","change":"0.00004%","rankChange":149}," Palpitoad          ":{"rank":" 641  ","usage":"  0.00003% ","change":"0.00003%","rankChange":131}," Trumbeak           ":{"rank":" 642  ","usage":"  0.00003% ","change":"-0.00002%","rankChange":15}," Chikorita          ":{"rank":" 643  ","usage":"  0.00003% ","change":"0%","rankChange":41}," Omanyte            ":{"rank":" 644  ","usage":"  0.00003% ","change":"-0.00009%","rankChange":-28}," Buizel             ":{"rank":" 645  ","usage":"  0.00003% ","change":"0%","rankChange":40}," Lumineon           ":{"rank":" 646  ","usage":"  0.00003% ","change":"0%","rankChange":33}," Cyndaquil          ":{"rank":" 647  ","usage":"  0.00003% ","change":"0.00003%","rankChange":89}," Mime Jr.           ":{"rank":" 648  ","usage":"  0.00003% ","change":"0.000019999999999999998%","rankChange":84}," Chespin            ":{"rank":" 649  ","usage":"  0.00003% ","change":"-0.00002%","rankChange":13}," Doduo              ":{"rank":" 650  ","usage":"  0.00003% ","change":"0.000009999999999999999%","rankChange":41}," Rhyhorn            ":{"rank":" 651  ","usage":"  0.00003% ","change":"0.00003%","rankChange":185}," Nidorina           ":{"rank":" 652  ","usage":"  0.00003% ","change":"0.00003%","rankChange":107}," Grimer             ":{"rank":" 653  ","usage":"  0.00003% ","change":"0.00003%","rankChange":159}," Spritzee           ":{"rank":" 654  ","usage":"  0.00002% ","change":"0.00002%","rankChange":197}," Graveler-Alola     ":{"rank":" 655  ","usage":"  0.00002% ","change":"-0.00095%","rankChange":-157}," Stufful            ":{"rank":" 656  ","usage":"  0.00002% ","change":"-0.00016%","rankChange":-58}," Buneary            ":{"rank":" 657  ","usage":"  0.00002% ","change":"-0.0025499999999999997%","rankChange":-238}," Mudkip             ":{"rank":" 658  ","usage":"  0.00002% ","change":"-0.00011999999999999999%","rankChange":-46}," Oshawott           ":{"rank":" 659  ","usage":"  0.00002% ","change":"-0.00411%","rankChange":-279}," Bergmite           ":{"rank":" 660  ","usage":"  0.00002% ","change":"0.00002%","rankChange":228}," Pidgey             ":{"rank":" 661  ","usage":"  0.00002% ","change":"0.00002%","rankChange":171}," Noibat             ":{"rank":" 662  ","usage":"  0.00002% ","change":"0.00002%","rankChange":142}," Luxio              ":{"rank":" 663  ","usage":"  0.00002% ","change":"0.00002%","rankChange":177}," Fomantis           ":{"rank":" 664  ","usage":"  0.00002% ","change":"0.00002%","rankChange":120}," Jangmo-o           ":{"rank":" 665  ","usage":"  0.00002% ","change":"-0.00002%","rankChange":5}," Snover             ":{"rank":" 666  ","usage":"  0.00002% ","change":"-0.000039999999999999996%","rankChange":-16}," Hoppip             ":{"rank":" 667  ","usage":"  0.00002% ","change":"0.00002%","rankChange":132}," Dewgong            ":{"rank":" 668  ","usage":"  0.00002% ","change":"-0.00033%","rankChange":-114}," Zubat              ":{"rank":" 669  ","usage":"  0.00002% ","change":"-0.00003%","rankChange":-15}," Grovyle            ":{"rank":" 670  ","usage":"  0.00001% ","change":"-0.000019999999999999998%","rankChange":8}," Grumpig            ":{"rank":" 671  ","usage":"  0.00001% ","change":"-0.00033999999999999997%","rankChange":-116}," Servine            ":{"rank":" 672  ","usage":"  0.00001% ","change":"0%","rankChange":58}," Geodude-Alola      ":{"rank":" 673  ","usage":"  0.00001% ","change":"-0.00028%","rankChange":-105}," Chinchou           ":{"rank":" 674  ","usage":"  0.00001% ","change":"0.00001%","rankChange":189}," Drilbur            ":{"rank":" 675  ","usage":"  0.00001% ","change":"-0.000059999999999999995%","rankChange":-31}," Bronzor            ":{"rank":" 676  ","usage":"  0.00001% ","change":"-0.00031%","rankChange":-117}," Beldum             ":{"rank":" 677  ","usage":"  0.00001% ","change":"0.00001%","rankChange":68}," Combee             ":{"rank":" 678  ","usage":"  0.00001% ","change":"0.00001%","rankChange":104}," Sneasel            ":{"rank":" 679  ","usage":"  0.00001% ","change":"-0.00134%","rankChange":-208}," Pignite            ":{"rank":" 680  ","usage":"  0.00001% ","change":"-0.00028%","rankChange":-109}," Poliwag            ":{"rank":" 681  ","usage":"  0.00001% ","change":"0.00001%","rankChange":127}," Frogadier          ":{"rank":" 682  ","usage":"  0.00001% ","change":"-0.0005%","rankChange":-146}," Grubbin            ":{"rank":" 683  ","usage":"  0.00001% ","change":"0.00001%","rankChange":118}," Krokorok           ":{"rank":" 684  ","usage":"  0.00001% ","change":"0.00001%","rankChange":99}," Turtwig            ":{"rank":" 685  ","usage":"  0.00001% ","change":"-0.00014%","rankChange":-74}," Gabite             ":{"rank":" 686  ","usage":"  0.00001% ","change":"-0.00005%","rankChange":-39}," NidoranF           ":{"rank":" 687  ","usage":"  0.00001% ","change":"0.00001%","rankChange":200}," Bellsprout         ":{"rank":" 688  ","usage":"  0.00001% ","change":"0.00001%","rankChange":67}," Trubbish           ":{"rank":" 689  ","usage":"  0.00001% ","change":"0%","rankChange":32}," Duosion            ":{"rank":" 690  ","usage":"  0.00001% ","change":"-0.00009%","rankChange":-61}," Snorunt            ":{"rank":" 691  ","usage":"  0.00001% ","change":"0.00001%","rankChange":82}," Sealeo             ":{"rank":" 692  ","usage":"  0.00001% ","change":"-0.00019%","rankChange":-98}," Vanillite          ":{"rank":" 693  ","usage":"  0.00001% ","change":"0.00001%","rankChange":82}," Ledian             ":{"rank":" 694  ","usage":"  0.00001% ","change":"-0.00028%","rankChange":-124}," Croconaw           ":{"rank":" 695  ","usage":"  0.00001% ","change":"0.00001%","rankChange":44}," Purrloin           ":{"rank":" 696  ","usage":"  0.00001% ","change":"-0.00014%","rankChange":-89}," Aipom              ":{"rank":" 697  ","usage":"  0.00001% ","change":"-0.00022%","rankChange":-109}," Lickitung          ":{"rank":" 698  ","usage":"  0.00001% ","change":"0.00001%","rankChange":78}," Bunnelby           ":{"rank":" 699  ","usage":"  0.00001% ","change":"-0.00095%","rankChange":-199}," Roggenrola         ":{"rank":" 700  ","usage":"  0.00001% ","change":"0.00001%","rankChange":87}," Trapinch           ":{"rank":" 701  ","usage":"  0.00001% ","change":"0.00001%","rankChange":52}," Gothita            ":{"rank":" 702  ","usage":"  0.00001% ","change":"0.00001%","rankChange":168}," Delcatty           ":{"rank":" 703  ","usage":"  0.00001% ","change":"-0.00026%","rankChange":-126}," Herdier            ":{"rank":" 704  ","usage":"  0.00001% ","change":"0%","rankChange":0}," Poliwhirl          ":{"rank":" 705  ","usage":"  0.00001% ","change":"0.00001%","rankChange":86}," Teddiursa          ":{"rank":" 706  ","usage":"  0.00001% ","change":"0.00001%","rankChange":41}," Goldeen            ":{"rank":" 707  ","usage":"  0.00001% ","change":"-0.00028999999999999995%","rankChange":-143}," Chingling          ":{"rank":" 708  ","usage":"  0.00001% ","change":"0.00001%","rankChange":142}," Wormadam           ":{"rank":" 709  ","usage":"  0.00001% ","change":"0.00001%","rankChange":185}," Kadabra            ":{"rank":" 710  ","usage":"  0.00000% ","change":"-0.00005%","rankChange":-49}," Zigzagoon          ":{"rank":" 711  ","usage":"  0.00000% ","change":"-0.00001%","rankChange":16}," Krabby             ":{"rank":" 712  ","usage":"  0.00000% ","change":"0%","rankChange":135}," Oddish             ":{"rank":" 713  ","usage":"  0.00000% ","change":"0%","rankChange":124}," Skiddo             ":{"rank":" 714  ","usage":"  0.00000% ","change":"0%","rankChange":44}," Burmy              ":{"rank":" 715  ","usage":"  0.00000% ","change":"0%","rankChange":131}," Silvally-Rock      ":{"rank":" 716  ","usage":"  0.00000% ","change":"0%","rankChange":45}," Psyduck            ":{"rank":" 717  ","usage":"  0.00000% ","change":"0%","rankChange":62}," Fletchling         ":{"rank":" 718  ","usage":"  0.00000% ","change":"0%","rankChange":80}," Crabrawler         ":{"rank":" 719  ","usage":"  0.00000% ","change":"-0.00099%","rankChange":-224}," Cubchoo            ":{"rank":" 720  ","usage":"  0.00000% ","change":"0%","rankChange":91}," Cleffa             ":{"rank":" 721  ","usage":"  0.00000% ","change":"0%","rankChange":56}," Relicanth          ":{"rank":" 722  ","usage":"  0.00000% ","change":"-0.0003%","rankChange":-161}," Octillery          ":{"rank":" 723  ","usage":"  0.00000% ","change":"-0.00005%","rankChange":-63}," Houndour           ":{"rank":" 724  ","usage":"  0.00000% ","change":"0%","rankChange":72}," Gible              ":{"rank":" 725  ","usage":"  0.00000% ","change":"0%","rankChange":93}," Azurill            ":{"rank":" 726  ","usage":"  0.00000% ","change":"0%","rankChange":59}," Kricketot          ":{"rank":" 727  ","usage":"  0.00000% ","change":"-0.00059%","rankChange":-200}," Mankey             ":{"rank":" 728  ","usage":"  0.00000% ","change":"0%","rankChange":92}," Meowth             ":{"rank":" 729  ","usage":"  0.00000% ","change":"-0.00062%","rankChange":-204}," Morelull           ":{"rank":" 730  ","usage":"  0.00000% ","change":"-0.00017%","rankChange":-126}," Geodude            ":{"rank":" 731  ","usage":"  0.00000% ","change":"-0.00002%","rankChange":-45}," Corphish           ":{"rank":" 732  ","usage":"  0.00000% ","change":"-0.00002%","rankChange":-43}," Ponyta             ":{"rank":" 733  ","usage":"  0.00000% ","change":"-0.00028%","rankChange":-161}," Kabuto             ":{"rank":" 734  ","usage":"  0.00000% ","change":"0%","rankChange":119}," Budew              ":{"rank":" 735  ","usage":"  0.00000% ","change":"0%","rankChange":155}," Throh              ":{"rank":" 736  ","usage":"  0.00000% ","change":"-0.00157%","rankChange":-277}," Whismur            ":{"rank":" 737  ","usage":"  0.00000% ","change":"-0.0001%","rankChange":-110}," Wurmple            ":{"rank":" 738  ","usage":"  0.00000% ","change":"0%","rankChange":68}," Machop             ":{"rank":" 739  ","usage":"  0.00000% ","change":"0%","rankChange":132}," Shuppet            ":{"rank":" 740  ","usage":"  0.00000% ","change":"0%","rankChange":132}," Swablu             ":{"rank":" 741  ","usage":"  0.00000% ","change":"0%","rankChange":158}," Whirlipede         ":{"rank":" 742  ","usage":"  0.00000% ","change":"0%","rankChange":75}," Diglett-Alola      ":{"rank":" 743  ","usage":"  0.00000% ","change":"-0.00335%","rankChange":-348}," Meowth-Alola       ":{"rank":" 744  ","usage":"  0.00000% ","change":"0%","rankChange":8}," Tyrunt             ":{"rank":" 745  ","usage":"  0.00000% ","change":"0%","rankChange":22}," Brionne            ":{"rank":" 746  ","usage":"  0.00000% ","change":"-0.00028%","rankChange":-173}," Shelmet            ":{"rank":" 747  ","usage":"  0.00000% ","change":"-0.00163%","rankChange":-291}," Igglybuff          ":{"rank":" 748  ","usage":"  0.00000% ","change":"0%","rankChange":0}," Larvesta           ":{"rank":" 749  ","usage":"  0.00000% ","change":"0%","rankChange":94}," Dratini            ":{"rank":" 750  ","usage":"  0.00000% ","change":"0%","rankChange":13}," Flaaffy            ":{"rank":" 751  ","usage":"  0.00000% ","change":"0%","rankChange":104}," Popplio            ":{"rank":" 752  ","usage":"  0.00000% ","change":"-0.00001%","rankChange":-44}," Dwebble            ":{"rank":" 753  ","usage":"  0.00000% ","change":"0%","rankChange":16}," Inkay              ":{"rank":" 754  ","usage":"  0.00000% ","change":"-0.00047%","rankChange":-214}," Simisear           ":{"rank":" 755  ","usage":"  0.00000% ","change":"-0.00025%","rankChange":-173}," Slakoth            ":{"rank":" 756  ","usage":"  0.00000% ","change":"0%","rankChange":117}," Charmeleon         ":{"rank":" 757  ","usage":"  0.00000% ","change":"-0.00005%","rankChange":-93}," Clamperl           ":{"rank":" 758  ","usage":"  0.00000% ","change":"-0.00205%","rankChange":-319}," Nuzleaf            ":{"rank":" 759  ","usage":"  0.00000% ","change":"0%","rankChange":65}," Steenee            ":{"rank":" 760  ","usage":"  0.00000% ","change":"-0.00006%","rankChange":-107}," Kakuna             ":{"rank":" 761  ","usage":"  0.00000% ","change":"-0.00001%","rankChange":-46}," Growlithe          ":{"rank":" 762  ","usage":"  0.00000% ","change":"-0.00038%","rankChange":-211}," Abra               ":{"rank":" 763  ","usage":"  0.00000% ","change":"-0.00005%","rankChange":-104}," Phantump           ":{"rank":" 764  ","usage":"  0.00000% ","change":"-0.00019%","rankChange":-168}," Minccino           ":{"rank":" 765  ","usage":"  0.00000% ","change":"-0.00001%","rankChange":-60}," Duskull            ":{"rank":" 766  ","usage":"  0.00000% ","change":"-0.00003%","rankChange":-91}," Bagon              ":{"rank":" 767  ","usage":"  0.00000% ","change":"0%","rankChange":47}," Gourgeist-Small    ":{"rank":" 768  ","usage":"  0.00000% ","change":"-0.00043%","rankChange":-225}," Skitty             ":{"rank":" 769  ","usage":"  0.00000% ","change":"-0.00003%","rankChange":-96}," Horsea             ":{"rank":" 770  ","usage":"  0.00000% ","change":"-0.00001%","rankChange":-44}," Pawniard           ":{"rank":" 771  ","usage":"  0.00000% ","change":"-0.00022%","rankChange":-180}," Blitzle            ":{"rank":" 772  ","usage":"  0.00000% ","change":"0%","rankChange":121}," Wimpod             ":{"rank":" 773  ","usage":"  0.00000% ","change":"-0.00004%","rankChange":-105}," Shellder           ":{"rank":" 774  ","usage":"  0.00000% ","change":"-0.00006%","rankChange":-128}," Lombre             ":{"rank":" 775  ","usage":"  0.00000% ","change":"0%","rankChange":58}," Happiny            ":{"rank":" 776  ","usage":"  0.00000% ","change":"-0.00001%","rankChange":-59}," Heatmor            ":{"rank":" 777  ","usage":"  0.00000% ","change":"-0.0029%","rankChange":-371}," Seel               ":{"rank":" 778  ","usage":"  0.00000% ","change":"0%","rankChange":86}," Axew               ":{"rank":" 779  ","usage":"  0.00000% ","change":"-0.00009%","rankChange":-146}," Makuhita           ":{"rank":" 780  ","usage":"  0.00000% ","change":"0%","rankChange":105}," Magby              ":{"rank":" 781  ","usage":"  0.00000% ","change":"-0.0001%","rankChange":-153}," Sandshrew-Alola    ":{"rank":" 782  ","usage":"  0.00000% ","change":"-0.00002%","rankChange":-94}," Venipede           ":{"rank":" 783  ","usage":"  0.00000% ","change":"0%","rankChange":783}," Yungoos            ":{"rank":" 784  ","usage":"  0.00000% ","change":"-0.00039%","rankChange":-235}," Tentacool          ":{"rank":" 785  ","usage":"  0.00000% ","change":"-0.00005%","rankChange":-127}," Deino              ":{"rank":" 786  ","usage":"  0.00000% ","change":"-0.00003%","rankChange":-109}," NidoranM           ":{"rank":" 787  ","usage":"  0.00000% ","change":"0%","rankChange":-21}," Nidorino           ":{"rank":" 788  ","usage":"  0.00000% ","change":"0%","rankChange":34}," Gloom              ":{"rank":" 789  ","usage":"  0.00000% ","change":"0%","rankChange":49}," Paras              ":{"rank":" 790  ","usage":"  0.00000% ","change":"-0.00095%","rankChange":-289}," Frillish           ":{"rank":" 791  ","usage":"  0.00000% ","change":"-0.00003%","rankChange":-117}," Tyrogue            ":{"rank":" 792  ","usage":"  0.00000% ","change":"0%","rankChange":3}," Wailmer            ":{"rank":" 793  ","usage":"  0.00000% ","change":"0%","rankChange":35}," Pumpkaboo-Small    ":{"rank":" 794  ","usage":"  0.00000% ","change":"0%","rankChange":104}," Marshtomp          ":{"rank":" 795  ","usage":"  0.00000% ","change":"-0.00008%","rankChange":-156}," Ledyba             ":{"rank":" 796  ","usage":"  0.00000% ","change":"0%","rankChange":-15}," Tepig              ":{"rank":" 797  ","usage":"  0.00000% ","change":"-0.00001%","rankChange":-62}," Honedge            ":{"rank":" 798  ","usage":"  0.00000% ","change":"0%","rankChange":25}," Sandshrew          ":{"rank":" 799  ","usage":"  0.00000% ","change":"0%","rankChange":-9}," Elekid             ":{"rank":" 800  ","usage":"  0.00000% ","change":"0%","rankChange":-60}," Natu               ":{"rank":" 801  ","usage":"  0.00000% ","change":"-0.00057%","rankChange":-272}," Cherubi            ":{"rank":" 802  ","usage":"  0.00000% ","change":"0%","rankChange":58}," Pancham            ":{"rank":" 803  ","usage":"  0.00000% ","change":"0%","rankChange":-52}," Espurr             ":{"rank":" 804  ","usage":"  0.00000% ","change":"0%","rankChange":82}," Munna              ":{"rank":" 805  ","usage":"  0.00000% ","change":"0%","rankChange":95}," Purugly            ":{"rank":" 806  ","usage":"  0.00000% ","change":"-0.00107%","rankChange":-322}," Bounsweet          ":{"rank":" 807  ","usage":"  0.00000% ","change":"0%","rankChange":-5}," Lairon             ":{"rank":" 808  ","usage":"  0.00000% ","change":"-0.00003%","rankChange":-136}," Grimer-Alola       ":{"rank":" 809  ","usage":"  0.00000% ","change":"-0.00011%","rankChange":-186}," Jigglypuff         ":{"rank":" 810  ","usage":"  0.00000% ","change":"-0.00068%","rankChange":-292}," Dewpider           ":{"rank":" 811  ","usage":"  0.00000% ","change":"-0.00012%","rankChange":-194}," Croagunk           ":{"rank":" 812  ","usage":"  0.00000% ","change":"0%","rankChange":66}," Electrike          ":{"rank":" 813  ","usage":"  0.00000% ","change":"0%","rankChange":66}," Panpour            ":{"rank":" 814  ","usage":"  0.00000% ","change":"0%","rankChange":-4}," Spoink             ":{"rank":" 815  ","usage":"  0.00000% ","change":"0%","rankChange":-2}," Swadloon           ":{"rank":" 816  ","usage":"  0.00000% ","change":"0%","rankChange":-67}," Elgyem             ":{"rank":" 817  ","usage":"  0.00000% ","change":"0%","rankChange":817}," Vulpix             ":{"rank":" 818  ","usage":"  0.00000% ","change":"0%","rankChange":-58}," Lillipup           ":{"rank":" 819  ","usage":"  0.00000% ","change":"0%","rankChange":-57}," Poochyena          ":{"rank":" 820  ","usage":"  0.00000% ","change":"0%","rankChange":10}," Phanpy             ":{"rank":" 821  ","usage":"  0.00000% ","change":"0%","rankChange":40}," Maractus           ":{"rank":" 822  ","usage":"  0.00000% ","change":"-0.0003%","rankChange":-260}," Scatterbug         ":{"rank":" 823  ","usage":"  0.00000% ","change":"0%","rankChange":-86}," Venonat            ":{"rank":" 824  ","usage":"  0.00000% ","change":"0%","rankChange":56}," Tympole            ":{"rank":" 825  ","usage":"  0.00000% ","change":"0%","rankChange":-47}," Ekans              ":{"rank":" 826  ","usage":"  0.00000% ","change":"0%","rankChange":32}," Koffing            ":{"rank":" 827  ","usage":"  0.00000% ","change":"0%","rankChange":-39}," Rufflet            ":{"rank":" 828  ","usage":"  0.00000% ","change":"0%","rankChange":13}," Pidove             ":{"rank":" 829  ","usage":"  0.00000% ","change":"0%","rankChange":5}," Larvitar           ":{"rank":" 830  ","usage":"  0.00000% ","change":"-0.00001%","rankChange":-119}," Pupitar            ":{"rank":" 831  ","usage":"  0.00000% ","change":"0%","rankChange":-45}," Lotad              ":{"rank":" 832  ","usage":"  0.00000% ","change":"-0.00007%","rankChange":-189}," Eelektrik          ":{"rank":" 833  ","usage":"  0.00000% ","change":"0%","rankChange":58}," Spearow            ":{"rank":" 834  ","usage":"  0.00000% ","change":"0%","rankChange":-91}," Anorith            ":{"rank":" 835  ","usage":"  0.00000% ","change":"-0.00002%","rankChange":-142}," Flabebe            ":{"rank":" 836  ","usage":"  0.00000% ","change":"0%","rankChange":-27}," Vibrava            ":{"rank":" 837  ","usage":"  0.00000% ","change":"0%","rankChange":38}," Lampent            ":{"rank":" 838  ","usage":"  0.00000% ","change":"0%","rankChange":-84}," Quilladin          ":{"rank":" 839  ","usage":"  0.00000% ","change":"-0.00002%","rankChange":-147}," Petilil            ":{"rank":" 840  ","usage":"  0.00000% ","change":"0%","rankChange":27}," Meditite           ":{"rank":" 841  ","usage":"  0.00000% ","change":"0%","rankChange":11}," Drowzee            ":{"rank":" 842  ","usage":"  0.00000% ","change":"-0.00001%","rankChange":-122}," Piplup             ":{"rank":" 843  ","usage":"  0.00000% ","change":"-0.00003%","rankChange":-161}," Golett             ":{"rank":" 844  ","usage":"  0.00000% ","change":"0%","rankChange":-79}," Sewaddle           ":{"rank":" 845  ","usage":"  0.00000% ","change":"0%","rankChange":17}," Timburr            ":{"rank":" 846  ","usage":"  0.00000% ","change":"0%","rankChange":36}," Cascoon            ":{"rank":" 847  ","usage":"  0.00000% ","change":"0%","rankChange":22}," Goomy              ":{"rank":" 848  ","usage":"  0.00000% ","change":"-0.00001%","rankChange":-119}," Grotle             ":{"rank":" 849  ","usage":"  0.00000% ","change":"-0.00002%","rankChange":-147}," Fennekin           ":{"rank":" 850  ","usage":"  0.00000% ","change":"-0.00148%","rankChange":-385}," Klang              ":{"rank":" 851  ","usage":"  0.00000% ","change":"-0.00004%","rankChange":-186}," Pumpkaboo-Large    ":{"rank":" 852  ","usage":"  0.00000% ","change":"0%","rankChange":852}," Gourgeist-Large    ":{"rank":" 853  ","usage":"  0.00000% ","change":"-0.00003%","rankChange":-170}," Seedot             ":{"rank":" 854  ","usage":"  0.00000% ","change":"0%","rankChange":-12}," Snubbull           ":{"rank":" 855  ","usage":"  0.00000% ","change":"0%","rankChange":28}," Skrelp             ":{"rank":" 856  ","usage":"  0.00000% ","change":"-0.00002%","rankChange":-162}," Binacle            ":{"rank":" 857  ","usage":"  0.00000% ","change":"0%","rankChange":-38}," Swirlix            ":{"rank":" 858  ","usage":"  0.00000% ","change":"-0.00004%","rankChange":-192}," Pansear            ":{"rank":" 859  ","usage":"  0.00000% ","change":"0%","rankChange":-2}," Pansage            ":{"rank":" 860  ","usage":"  0.00000% ","change":"-0.00001%","rankChange":-138}," Skiploom           ":{"rank":" 861  ","usage":"  0.00000% ","change":"-0.0003%","rankChange":-295}," Remoraid           ":{"rank":" 862  ","usage":"  0.00000% ","change":"0%","rankChange":22}," Vanillish          ":{"rank":" 863  ","usage":"  0.00000% ","change":"-0.00001%","rankChange":-138}," Zweilous           ":{"rank":" 864  ","usage":"  0.00000% ","change":"0%","rankChange":-93}," Weepinbell         ":{"rank":" 865  ","usage":"  0.00000% ","change":"-0.00002%","rankChange":-170}," Woobat             ":{"rank":" 866  ","usage":"  0.00000% ","change":"-0.00004%","rankChange":-199}," Gulpin             ":{"rank":" 867  ","usage":"  0.00000% ","change":"0%","rankChange":-126}," Wingull            ":{"rank":" 868  ","usage":"  0.00000% ","change":"0%","rankChange":-33}," Mareep             ":{"rank":" 869  ","usage":"  0.00000% ","change":"0%","rankChange":20}," Barboach           ":{"rank":" 870  ","usage":"  0.00000% ","change":"-0.00001%","rankChange":-142}," Klink              ":{"rank":" 871  ","usage":"  0.00000% ","change":"0%","rankChange":871}," Surskit            ":{"rank":" 872  ","usage":"  0.00000% ","change":"0%","rankChange":-56}," Baltoy             ":{"rank":" 873  ","usage":"  0.00000% ","change":"0%","rankChange":-17}," Spheal             ":{"rank":" 874  ","usage":"  0.00000% ","change":"0%","rankChange":-26}," Shroomish          ":{"rank":" 875  ","usage":"  0.00000% ","change":"0%","rankChange":17}," Floette            ":{"rank":" 876  ","usage":"  0.00000% ","change":"0%","rankChange":-126}," Prinplup           ":{"rank":" 877  ","usage":"  0.00000% ","change":"0%","rankChange":4}," Spewpa             ":{"rank":" 878  ","usage":"  0.00000% ","change":"-0.00002%","rankChange":-191}," Foongus            ":{"rank":" 879  ","usage":"  0.00000% ","change":"0%","rankChange":16}," Silcoon            ":{"rank":" 880  ","usage":"  0.00000% ","change":"-0.0001%","rankChange":-254}," Skorupi            ":{"rank":" 881  ","usage":"  0.00000% ","change":"0%","rankChange":-50}," Pumpkaboo-Super    ":{"rank":" 882  ","usage":"  0.00000% ","change":"-0.00058%","rankChange":-354}," Hoothoot           ":{"rank":" 883  ","usage":"  0.00000% ","change":"0%","rankChange":-39}," Clauncher          ":{"rank":" 884  ","usage":"  0.00000% ","change":"0%","rankChange":13}," Slugma             ":{"rank":" 885  ","usage":"  0.00000% ","change":"-0.00003%","rankChange":-204}," Finneon            ":{"rank":" 886  ","usage":"  0.00000% ","change":"-0.00848%","rankChange":-571}," Sandile            ":{"rank":" 887  ","usage":"  0.00000% ","change":"0%","rankChange":-119}," Smoochum           ":{"rank":" 888  ","usage":"  0.00000% ","change":"-0.00002%","rankChange":-191}," Stunky             ":{"rank":" 889  ","usage":"  0.00000% ","change":"0%","rankChange":-84}," Karrablast         ":{"rank":" 890  ","usage":"  0.00000% ","change":"0%","rankChange":890}," Nincada            ":{"rank":" 891  ","usage":"  0.00000% ","change":"0%","rankChange":-84}," Glameow            ":{"rank":" 892  ","usage":"  0.00000% ","change":"0%","rankChange":-89}," Helioptile         ":{"rank":" 893  ","usage":"  0.00000% ","change":"0%","rankChange":-16}," Sliggoo            ":{"rank":" 894  ","usage":"  0.00000% ","change":"0%","rankChange":-100}," Mantyke            ":{"rank":" 895  ","usage":"  0.00000% ","change":"0%","rankChange":-149}," Loudred            ":{"rank":" 896  ","usage":"  0.00000% ","change":"-0.00001%","rankChange":-162}," Yamask             ":{"rank":" 897  ","usage":"  0.00000% ","change":"0%","rankChange":-159}," Litleo             ":{"rank":" 898  ","usage":"  0.00000% ","change":"0%","rankChange":-53}," Darumaka           ":{"rank":" 899  ","usage":"  0.00000% ","change":"0%","rankChange":-50}," Litwick            ":{"rank":" 900  ","usage":"  0.00000% ","change":"0%","rankChange":-108}," Mienfoo            ":{"rank":" 901  ","usage":"  0.00000% ","change":"0%","rankChange":-75}," Deerling           ":{"rank":" 902  ","usage":"  0.00000% ","change":"0%","rankChange":-145}," Tynamo             ":{"rank":" 903  ","usage":"  0.00000% ","change":"0%","rankChange":-123}," Tranquill          ":{"rank":" 904  ","usage":"  0.00000% ","change":"0%","rankChange":-38}," Exeggcute          ":{"rank":" 905  ","usage":"  0.00000% ","change":"0%","rankChange":-135}}